同步异步电路/快时钟域控制信号同步到慢时钟域/f2s_control.v
/*参考刘清帆CSDN:【SOC架构】（一）同步与异步信号*/
/*快时钟域控制信号同步到慢时钟域*/
module f2s_control(
    input       adat,
                rst,
                aclk,
                bclk,
    output  reg bdat
);
reg     adat1,
        bdat1,  bdat2,  bdat3,
        abdat1, abdat2;
//实例化慢时钟域同步器
always @(posedge bclk) begin
    {bdat2,bdat1}<={bdat1,adat1};
end
//实例化快时钟域同步器
always @(posedge aclk) begin
    {abdat2,abdat1}<={abdat1,bdat2};
end
//实例化快时钟域同步慢时钟域方法：缩短
always @(posedge bclk or negedge rst) begin
    if(~rst)
        bdat3<=1'b0;
    else
        bdat3<=bdat2;
end
always @(bdat3,bdat2) begin
    bdat<=({bdat3,bdat2}==2'b01)?1'b1:1'b0;
end


//实例化慢时钟域同步快时钟域方法：反馈延时
always @(posedge aclk or negedge rst) begin
    if(~rst)
        adat1<=1'b0;
    else    //adat触发，abdat2关闭
        if(abdat2)
            adat1<=1'b0;
        else
            if(adat)
                adat1<=1'b1;
end
endmodule

同步异步电路/快时钟域控制信号同步到慢时钟域/f2s_conrtol_tb.v
/*参考刘清帆CSDN:【SOC架构】（一）同步与异步信号*/
/*快时钟域控制信号同步到慢时钟域*/
/*测试*/
`timescale 1ns/1ns
`include "f2s_control.v"
module f2s_control_tb;
//************<端口声明>****************
reg         adat,
            rst,
            aclk,
            bclk;
wire        bdat;
//***********<模块例化>******************
f2s_control M1(
    adat,
    rst,
    aclk,
    bclk,
    bdat
);
initial begin
    $dumpfile("f2s_control.vcd");
    $dumpvars;
    aclk<=0;
    bclk<=0;
    rst<=0;
    adat<=0;
    #12 rst<=1;
    #20 @(posedge aclk)  adat<=1;
    @(posedge aclk)  adat<=0;
    #1000   $finish;
end
always #7 
    aclk<=~aclk;
always #10 
    bclk<=~bclk;
endmodule

同步异步电路/快时钟域控制信号同步到慢时钟域/f2s_control.vcd
$date
	Mon Feb 06 16:26:08 2023
$end
$version
	Icarus Verilog
$end
$timescale
	1ns
$end
$scope module f2s_control_tb $end
$var wire 1 ! bdat $end
$var reg 1 " aclk $end
$var reg 1 # adat $end
$var reg 1 $ bclk $end
$var reg 1 % rst $end
$scope module M1 $end
$var wire 1 " aclk $end
$var wire 1 # adat $end
$var wire 1 $ bclk $end
$var wire 1 % rst $end
$var reg 1 & abdat1 $end
$var reg 1 ' abdat2 $end
$var reg 1 ( adat1 $end
$var reg 1 ! bdat $end
$var reg 1 ) bdat1 $end
$var reg 1 * bdat2 $end
$var reg 1 + bdat3 $end
$upscope $end
$upscope $end
$enddefinitions $end
$comment Show the parameter values. $end
$dumpall
$end
#0
$dumpvars
0+
0*
0)
0(
0'
0&
0%
0$
0#
0"
0!
$end
#7
1"
#10
1$
#12
1%
#14
0"
#20
0$
#21
1"
#28
0"
#30
1$
#35
1#
1"
#40
0$
#42
0"
#49
1(
0#
1"
#50
1)
1$
#56
0"
#60
0$
#63
1"
#70
1!
1*
0"
1$
#77
1&
1"
#80
0$
#84
0"
#90
0!
1+
1$
#91
1'
1"
#98
0"
#100
0$
#105
0(
1"
#110
0)
1$
#112
0"
#119
1"
#120
0$
#126
0"
#130
0*
1$
#133
0&
1"
#140
0"
0$
#147
0'
1"
#150
0+
1$
