常见数字电路/按键控灯(上升沿检测)/状态机法/button_light2.v
//按键控灯练习，见https://blog.csdn.net/SuperiorEE/article/details/128880282
//波形变换法，使用moore机
module button_light2#(
    parameter   S1=3'b001,      //one-hot encode state
                S2=3'b010,
                S3=3'b100
)
(
    input       clk     ,
                button  ,
                rst_n   ,
                
    output  reg light
);
reg [2:0]   current_state   ,
            next_state      ;
reg         button_d1       ,
            button_d2        ;
/*同步器，用于同步输入，避免亚稳态*/
always @(posedge clk or negedge rst_n) begin
    if(~rst_n)
        {button_d2,button_d1}<=2'b00;
    else
        {button_d2,button_d1}<={button_d1,button};
end
//第一段：现态次态切换
always @(posedge clk,negedge rst_n) begin
    if(~rst_n)
        current_state<=S1;          //状态复位
    else
        current_state<=next_state;  //状态转换
end
//第二段:次态组合逻辑
always@(*)begin
    case (current_state)
        S1:
            next_state=(button_d2==0)?S1:S2;
        S2:
            next_state=(button_d2==0)?S1:S3;
        S3:
            next_state=(button_d2==0)?S1:S3;
        default: 
            next_state=S1;
    endcase
end
//第三段:输出电路（可以是组合或者时序，根据mealy或者moore确定，时序电路可以避免输出随输入变化的毛刺，但是会比mealy慢一个时钟）
always@(posedge clk,negedge rst_n)begin
    if(~rst_n)
        light<=0;
    else if(current_state==S2)
        light<=~light;
        
end
endmodule

常见数字电路/按键控灯(上升沿检测)/状态机法/button_light_tb.v
`timescale 1ns/1ps
`include "button_light2.v"
module button_light_tb;
reg         rst_n   ,
            clk     ,
            button  ;
            
wire        light   ;

//模块例化
button_light2 b1(
            clk     ,
            button  ,
            rst_n   ,
                    
            light 
);
//激励
initial begin
            $dumpfile("button_light2.vcd");
            $dumpvars;
            
            clk<=0;
            rst_n<=0;
            button<=0;

    #15     rst_n<=1;
    #20     button<=1;
    #160    button<=0;
    #125    button<=1;
    #130    button<=0;
    #55     button<=1;
    #60     button<=0;
    #1000   $finish;
end
//时钟生成
always #10
    clk=~clk;
endmodule

常见数字电路/按键控灯(上升沿检测)/状态机法/button_light2.vcd
$date
	Sun Feb 26 22:50:08 2023
$end
$version
	Icarus Verilog
$end
$timescale
	1ps
$end
$scope module button_light_tb $end
$var wire 1 ! light $end
$var reg 1 " button $end
$var reg 1 # clk $end
$var reg 1 $ rst_n $end
$scope module b1 $end
$var wire 1 " button $end
$var wire 1 # clk $end
$var wire 1 $ rst_n $end
$var reg 1 % button_d1 $end
$var reg 1 & button_d2 $end
$var reg 3 ' current_state [2:0] $end
$var reg 1 ! light $end
$var reg 3 ( next_state [2:0] $end
$upscope $end
$upscope $end
$enddefinitions $end
#0
$dumpvars
b1 (
b1 '
0&
0%
0$
0#
0"
0!
$end
#10000
1#
#15000
1$
#20000
0#
#30000
1#
#35000
1"
#40000
0#
#50000
1%
1#
#60000
0#
#70000
b10 (
1&
1#
#80000
0#
#90000
b100 (
b10 '
1#
#100000
0#
#110000
b100 '
1!
1#
#120000
0#
#130000
1#
#140000
0#
#150000
1#
#160000
0#
#170000
1#
#180000
0#
#190000
1#
#195000
0"
#200000
0#
#210000
0%
1#
#220000
0#
#230000
b1 (
0&
1#
#240000
0#
#250000
b1 '
1#
#260000
0#
#270000
1#
#280000
0#
#290000
1#
#300000
0#
#310000
1#
#320000
1"
0#
#330000
1%
1#
#340000
0#
#350000
b10 (
1&
1#
#360000
0#
#370000
b100 (
b10 '
1#
#380000
0#
#390000
b100 '
0!
1#
#400000
0#
#410000
1#
#420000
0#
#430000
1#
#440000
0#
#450000
0"
1#
#460000
0#
#470000
0%
1#
#480000
0#
#490000
b1 (
0&
1#
#500000
0#
#505000
1"
#510000
1%
b1 '
1#
#520000
0#
#530000
b10 (
1&
1#
#540000
0#
#550000
b100 (
b10 '
1#
#560000
0#
#565000
0"
#570000
1!
b100 '
0%
1#
#580000
0#
#590000
b1 (
0&
1#
#600000
0#
#610000
b1 '
1#
