多位比较器的实现/compare_1bit.v
`timescale 1ns/100ps
module cmp(
    input   Gi,
    Ei,
    input   Ai,
    Bi,
    output  Go,
    Eo
  );
  assign  Eo=Ei&&(Ai==Bi);
  assign  Go=(Ai>Bi)||(Ai==Bi)&&Gi;
  //assign  Lo=(~Eo)&&(~Go);//不大不相等那肯定是小
endmodule

多位比较器的实现/compare_nbit.v
`timescale 1ns/100ps
`include "compare_1bit.v"
//*********<端口声明>*************
module cmp_n#
(
    parameter N=8
)
(
input   wire[N-1:0]     A, B,
output  wire            Go, Eo, Lo
);
//*********<中间信号>*************
wire [N:0]  Gi,Ei;
assign  Gi[0]=1'b0;
assign  Ei[0]=1'b1;
assign  Go=Gi[N];
assign  Eo=Ei[N];
assign  Lo=(~Go)&&(~Eo);
//*********<模块例化>*************
generate
    genvar i;
    for(i=0;i<8;i=i+1)begin
        cmp cmp2(
            Gi[i], Ei[i],
            A[i], B[i],
            Gi[i+1], Ei[i+1]
            );            
    end
endgenerate
endmodule

常见数字电路/多位比较器的实现/compare_nbit_tb.v
`timescale 1ns/100ps
`include "compare_nbit.v"
module  compare_nbit_tb;
parameter   N=8;
reg [N-1:0]     A, B;
wire            Go, Eo, Lo;
//*********<模块例化>*************
cmp_n 
#(
    .N(N)
)
cmp_8
(
    .A(A),
    .B(B),
    
    .Go(Go),
    .Eo(Eo),
    .Lo(Lo)
);
initial begin
    $dumpfile("cmp_n.vcd");
    $dumpvars;
    A='b0;
    B='b0;
    repeat(20)  begin
      #10   A=$random;B=$random;
    end
    #500 $finish;
end



endmodule

多位比较器的实现/cmp_n.vcd
$date
	Mon Nov 21 21:03:51 2022
$end
$version
	Icarus Verilog
$end
$timescale
	100ps
$end
$scope module compare_nbit_tb $end
$var wire 1 ! Lo $end
$var wire 1 " Go $end
$var wire 1 # Eo $end
$var parameter 32 $ N $end
$var reg 8 % A [7:0] $end
$var reg 8 & B [7:0] $end
$scope module cmp_8 $end
$var wire 8 ' A [7:0] $end
$var wire 8 ( B [7:0] $end
$var wire 1 ! Lo $end
$var wire 1 " Go $end
$var wire 9 ) Gi [8:0] $end
$var wire 1 # Eo $end
$var wire 9 * Ei [8:0] $end
$var parameter 32 + N $end
$scope begin genblk1[0] $end
$var parameter 2 , i $end
$scope module cmp2 $end
$var wire 1 - Ai $end
$var wire 1 . Bi $end
$var wire 1 / Ei $end
$var wire 1 0 Eo $end
$var wire 1 1 Gi $end
$var wire 1 2 Go $end
$upscope $end
$upscope $end
$scope begin genblk1[1] $end
$var parameter 2 3 i $end
$scope module cmp2 $end
$var wire 1 4 Ai $end
$var wire 1 5 Bi $end
$var wire 1 6 Ei $end
$var wire 1 7 Eo $end
$var wire 1 8 Gi $end
$var wire 1 9 Go $end
$upscope $end
$upscope $end
$scope begin genblk1[2] $end
$var parameter 3 : i $end
$scope module cmp2 $end
$var wire 1 ; Ai $end
$var wire 1 < Bi $end
$var wire 1 = Ei $end
$var wire 1 > Eo $end
$var wire 1 ? Gi $end
$var wire 1 @ Go $end
$upscope $end
$upscope $end
$scope begin genblk1[3] $end
$var parameter 3 A i $end
$scope module cmp2 $end
$var wire 1 B Ai $end
$var wire 1 C Bi $end
$var wire 1 D Ei $end
$var wire 1 E Eo $end
$var wire 1 F Gi $end
$var wire 1 G Go $end
$upscope $end
$upscope $end
$scope begin genblk1[4] $end
$var parameter 4 H i $end
$scope module cmp2 $end
$var wire 1 I Ai $end
$var wire 1 J Bi $end
$var wire 1 K Ei $end
$var wire 1 L Eo $end
$var wire 1 M Gi $end
$var wire 1 N Go $end
$upscope $end
$upscope $end
$scope begin genblk1[5] $end
$var parameter 4 O i $end
$scope module cmp2 $end
$var wire 1 P Ai $end
$var wire 1 Q Bi $end
$var wire 1 R Ei $end
$var wire 1 S Eo $end
$var wire 1 T Gi $end
$var wire 1 U Go $end
$upscope $end
$upscope $end
$scope begin genblk1[6] $end
$var parameter 4 V i $end
$scope module cmp2 $end
$var wire 1 W Ai $end
$var wire 1 X Bi $end
$var wire 1 Y Ei $end
$var wire 1 Z Eo $end
$var wire 1 [ Gi $end
$var wire 1 \ Go $end
$upscope $end
$upscope $end
$scope begin genblk1[7] $end
$var parameter 4 ] i $end
$scope module cmp2 $end
$var wire 1 ^ Ai $end
$var wire 1 _ Bi $end
$var wire 1 ` Ei $end
$var wire 1 a Eo $end
$var wire 1 b Gi $end
$var wire 1 c Go $end
$upscope $end
$upscope $end
$upscope $end
$upscope $end
$enddefinitions $end
$comment Show the parameter values. $end
$dumpall
b111 ]
b110 V
b101 O
b100 H
b11 A
b10 :
b1 3
b0 ,
b1000 +
b1000 $
$end
#0
$dumpvars
0c
0b
1a
1`
0_
0^
0\
0[
1Z
1Y
0X
0W
0U
0T
1S
1R
0Q
0P
0N
0M
1L
1K
0J
0I
0G
0F
1E
1D
0C
0B
0@
0?
1>
1=
0<
0;
09
08
17
16
05
04
02
01
10
1/
0.
0-
b111111111 *
b0 )
b0 (
b0 '
b0 &
b0 %
1#
0"
0!
$end
#100
1T
0R
1N
0L
0=
1!
0K
1M
0`
1b
07
0E
1G
0Z
1\
06
0#
0D
0Y
00
0a
0>
1F
b1 *
0S
1[
1@
b11111000 )
1U
1.
1_
1;
1P
b10000001 &
b10000001 (
b100100 %
b100100 '
#200
1!
0b
0"
0\
0c
16
b11 *
10
0F
0[
0@
b110000 )
0U
15
1Q
1X
0_
1-
0;
1B
0P
b1100011 &
b1100011 (
b1001 %
b1001 '
#300
1`
1Z
1Y
1S
1R
1L
1K
0b
1E
0\
1D
0T
1>
0N
0[
1=
0U
b11111111 *
17
0M
b0 )
0G
05
1<
1C
0Q
0X
1_
1;
b10001101 &
b10001101 (
b1101 %
b1101 '
#400
0K
1M
0!
0E
1G
1"
06
0=
0D
0R
0#
1c
0Y
0`
00
18
07
0>
1F
0L
0a
0S
1[
b1 *
0Z
1b
12
1@
1U
b111011010 )
1\
0.
15
0<
0C
1J
0_
0B
1P
1W
b10010 &
b10010 (
b1100101 %
b1100101 '
#500
1!
1=
0"
17
0?
0M
0T
0c
16
09
0G
0N
b111 *
10
08
0F
0[
0b
02
0@
0U
b0 )
0\
1.
05
1<
1C
0J
0;
0P
0W
b1101 &
b1101 (
b1 %
b1 '
#600
0!
1F
1"
1@
1c
06
0=
0D
00
07
1?
b1 *
0>
1b
19
b110001100 )
1\
1J
1Q
0-
14
1;
1I
1P
1W
b111101 &
b111101 (
b1110110 %
b1110110 '
#700
1T
1N
1F
1@
1M
1G
18
1[
1?
12
1U
b111111110 )
19
0.
0J
0Q
1_
1-
04
1B
0I
1^
b10001100 &
b10001100 (
b11101101 %
b11101101 '
#800
0!
1"
0?
1c
0F
09
0@
1b
b111110010 )
1\
15
0C
1X
0;
1I
b11000110 &
b11000110 (
b11111001 %
b11111001 '
#900
1F
0M
0T
0[
1@
0G
0N
b110001010 )
0U
0<
1C
1Q
0X
1;
0B
0I
0P
b10101010 &
b10101010 (
b11000101 %
b11000101 '
#1000
0M
16
0G
b11 *
10
08
0F
0b
02
0@
b100000000 )
0\
1.
1<
0C
1J
1X
0_
1P
b1110111 &
b1110111 (
b11100101 %
b11100101 '
#1100
1b
1\
1[
1U
1!
06
0=
1T
00
b1 *
07
0"
1N
b11100000 )
0c
1C
0J
0Q
0X
1_
0-
14
0;
1I
0P
0W
0^
b10001111 &
b10001111 (
b10010 %
b10010 '
#1200
0!
1=
17
1"
16
b111100000 )
1c
b111 *
10
0.
1X
1P
1W
1^
b11001110 &
b11001110 (
b11110010 %
b11110010 '
#1300
0=
07
06
b1 *
00
1M
1T
1G
b111110000 )
1N
1.
05
0C
04
1B
0I
b11000101 &
b11000101 (
b11101000 %
b11101000 '
#1400
1!
0T
0N
0"
0c
0M
0[
0G
b10000000 )
0U
1C
1J
1Q
0X
1;
1I
0P
0^
b10111101 &
b10111101 (
b1011100 %
b1011100 '
#1500
1[
1U
1D
1>
1T
1=
1N
17
16
1M
b1111 *
10
0b
1G
b1110000 )
0\
0C
0J
1X
0_
1-
0I
1P
0W
b1100101 &
b1100101 (
b101101 %
b101101 '
#1600
1F
0D
1@
0!
0>
0=
1?
1"
0T
07
19
1c
0N
06
b1 *
00
18
1b
0M
12
1\
b111001110 )
0G
0.
15
0<
1C
0Q
0X
14
0;
0B
1W
b1010 &
b1010 (
b1100011 %
b1100011 '
#1700
1R
1L
1K
1E
0F
0T
1D
0@
0N
1>
1=
0?
0M
17
09
0G
16
b111111 *
10
08
0[
0b
02
0U
b100000000 )
0\
05
0C
1Q
0-
04
0P
0W
1^
b100000 &
b100000 (
b10000000 %
b10000000 '
#1800
0K
1b
0E
1\
0!
06
0D
0R
0=
00
0>
0L
1[
1"
b1 *
07
1?
1U
1c
b111000100 )
19
1.
1<
1C
1J
0Q
1_
14
1B
1P
b10011101 &
b10011101 (
b10101010 %
b10101010 '
#1900
1T
1N
1M
1b
1G
1\
0?
1F
1[
09
1@
b111111000 )
1U
15
0<
0C
0_
1;
0B
1I
0P
b10011 &
b10011 (
b10010110 %
b10010110 '
#2000
0[
0U
0b
0T
1!
0\
16
0N
b11 *
10
0"
b11000 )
0c
1X
1-
04
1B
0I
0^
b1010011 &
b1010011 (
b1101 %
b1101 '
