MCDF/formatter/formatter.v
/***************<MCDF 整形器 formatter>*********************/
`timescale 1ns/100ps
/***************<端口声明>*********************/
module formatter
(
    input   wire            clk_i,
                            rstn_i,

    input   wire            a2f_val_i,//!!!这个信号没用到，检查是否可以去除
    input   wire    [1:0]   a2f_id_i,
    input   wire    [31:0]  a2f_data_i,
    input   wire    [2:0]   a2f_pkglen_sel_i,

    input   wire            fmt_grant_i,
    
    input   wire            a2f_end_i,//增加的信号，在arbiter中判断end更方便
    
    output  wire            f2a_ack_o,
    output  reg             fmt_id_req_o,

    output  wire    [1:0]   fmt_child_o,
    output  reg     [5:0]   fmt_length_o,
    output  wire            fmt_req_o,
    output  wire    [31:0]  fmt_data_o,
    output  reg             fmt_start_o,
    output  wire            fmt_end_o

);
/***************<中间信号>*********************/
reg fmt_end_d1;//end信号时延一个周期

/***************<时序电路>*********************/
// >>>fmt_end_d1用于产生fmt_id_req_o,并保证两次发送之间的时隙
//end信号时延一个周期
always @(posedge clk_i or negedge rstn_i) begin
    if(~rstn_i)
        fmt_end_d1<=0;
    else
        fmt_end_d1<=fmt_end_o;
end
// >>>fmt_id_req_o<<<
//1产生向下握手信号 fmt_id_req_o，等待优先通道不为11
always @(posedge clk_i or negedge rstn_i) begin
    if(~rstn_i)begin
        fmt_id_req_o<=1;//复位时没有发送占用，因此可以向下级握手
    end
    else if(fmt_end_d1)begin//因为end和start并不会重合，所以谁先谁后判断不影响
        fmt_id_req_o<=1;
    end
    else if(fmt_grant_i)begin
        fmt_id_req_o<=0;
    end
    else
        fmt_id_req_o<=fmt_id_req_o;
end
// >>> fmt_start_o 是f2a_ack_o延迟一个周期
always @(posedge clk_i or negedge rstn_i) begin
    if(~rstn_i)
        fmt_start_o<=0;
    else
        fmt_start_o<=f2a_ack_o;
end
/***************<组合电路>*********************/
// >>>fmt_req_o<<<
//等待优先通道不为11，产生 fmt_req_o,表示下级就绪,当出现 fmt_grant_i 时再置低
//采用 波形变换 方式实现 优先通道不为11&fmt_id_req_o,参考时序参考图
assign  fmt_req_o=fmt_id_req_o & (a2f_id_i!=2'b11);
//波形变换，ack信号，在通道联通后，直送给slave
assign  f2a_ack_o=fmt_grant_i & fmt_req_o;
//一些直连信号
assign  fmt_end_o=a2f_end_i;//直连arbiter中的end信号（这个信号是另加的，因为arbiter中判断end更容易）
assign  fmt_data_o=a2f_data_i;
assign  fmt_child_o=a2f_id_i;
always @(*) begin//数据包长度译码（在slave_FIFO里面时用求幂实现）
    case(a2f_pkglen_sel_i) 
        3'b000:fmt_length_o<=6'd4;
        3'b001:fmt_length_o<=6'd8;
        3'b010:fmt_length_o<=6'd16;
        3'b011:fmt_length_o<=6'd32;
        default: 
            fmt_length_o<=6'd32;
    endcase
end

endmodule

MCDF/formatter/formatter_tb.v
`timescale 1ns/100ps
`include "formatter.v"
/*************************<端口声明>*********************/
module formatter_tb;
reg             clk_i;
reg             rstn_i;
reg             a2f_val_i;
reg     [1:0]   a2f_id_i;
reg     [31:0]  a2f_data_i;
reg     [2:0]   a2f_pkglen_sel_i;
reg             fmt_grant_i;
reg             a2f_end_i;          //增加的

wire            f2a_ack_o;
wire            fmt_id_req_o;
wire    [1:0]   fmt_child_o;
wire    [5:0]   fmt_length_o;
wire            fmt_req_o;
wire    [31:0]  fmt_data_o;
wire            fmt_start_o;
wire            fmt_end_o;
/*************************<实例化>*********************/
formatter fm1(
    clk_i,
    rstn_i,
    a2f_val_i,
    a2f_id_i,
    a2f_data_i,
    a2f_pkglen_sel_i,
    fmt_grant_i,
    a2f_end_i,       
    
    f2a_ack_o,
    fmt_id_req_o,
    fmt_child_o,
    fmt_length_o,
    fmt_req_o,
    fmt_data_o,
    fmt_start_o,
    fmt_end_o
);
/*************************<信号产生>*********************/
initial begin
        clk_i<=0;
        rstn_i<=0;

        a2f_val_i<=0;           //这个信号没用到
        
        a2f_id_i<=2'b11;         //接通的通道
        a2f_data_i<=$random;    //接通通道的数据
        a2f_pkglen_sel_i<=0;    //与a2f_id_i同步变化
        fmt_grant_i<=0;
        a2f_end_i<=0;  
        $dumpfile("formatter.vcd");
        $dumpvars;
#15     rstn_i<=1;
#40 
@(posedge clk_i)    a2f_id_i<=2'b00;
#30
@(posedge clk_i)    fmt_grant_i<=1;
@(posedge clk_i)    fmt_grant_i<=1;
@(posedge clk_i)    fmt_grant_i<=0;
@(posedge clk_i)    fmt_grant_i<=0;
@(posedge clk_i)    a2f_end_i<=1;
@(posedge clk_i)    a2f_end_i<=0;
#500    $finish;
end
always @(posedge clk_i) begin
    a2f_data_i<=$random;
end
always #10 clk_i<=~clk_i;
always @(*) begin//模拟arbiter中的信号同步
    case(a2f_id_i)
        2'b00:a2f_pkglen_sel_i<=3'b000;
        2'b01:a2f_pkglen_sel_i<=3'b001;
        2'b10:a2f_pkglen_sel_i<=3'b010;
        2'b11:a2f_pkglen_sel_i<=3'b000;
    endcase
end
endmodule

MCDF/formatter/formatter.vcd
$date
	Wed Dec  7 13:15:39 2022
$end
$version
	Icarus Verilog
$end
$timescale
	100ps
$end
$scope module formatter_tb $end
$var wire 1 ! fmt_start_o $end
$var wire 1 " fmt_req_o $end
$var wire 6 # fmt_length_o [5:0] $end
$var wire 1 $ fmt_id_req_o $end
$var wire 1 % fmt_end_o $end
$var wire 32 & fmt_data_o [31:0] $end
$var wire 2 ' fmt_child_o [1:0] $end
$var wire 1 ( f2a_ack_o $end
$var reg 32 ) a2f_data_i [31:0] $end
$var reg 1 * a2f_end_i $end
$var reg 2 + a2f_id_i [1:0] $end
$var reg 3 , a2f_pkglen_sel_i [2:0] $end
$var reg 1 - a2f_val_i $end
$var reg 1 . clk_i $end
$var reg 1 / fmt_grant_i $end
$var reg 1 0 rstn_i $end
$scope module fm1 $end
$var wire 32 1 a2f_data_i [31:0] $end
$var wire 1 * a2f_end_i $end
$var wire 2 2 a2f_id_i [1:0] $end
$var wire 3 3 a2f_pkglen_sel_i [2:0] $end
$var wire 1 - a2f_val_i $end
$var wire 1 . clk_i $end
$var wire 1 ( f2a_ack_o $end
$var wire 2 4 fmt_child_o [1:0] $end
$var wire 32 5 fmt_data_o [31:0] $end
$var wire 1 % fmt_end_o $end
$var wire 1 / fmt_grant_i $end
$var wire 1 " fmt_req_o $end
$var wire 1 0 rstn_i $end
$var reg 1 6 fmt_end_d1 $end
$var reg 1 $ fmt_id_req_o $end
$var reg 6 7 fmt_length_o [5:0] $end
$var reg 1 ! fmt_start_o $end
$upscope $end
$upscope $end
$enddefinitions $end
#0
$dumpvars
b100 7
06
b10010000101010011010100100100 5
b11 4
b0 3
b11 2
b10010000101010011010100100100 1
00
0/
0.
0-
b0 ,
b11 +
0*
b10010000101010011010100100100 )
0(
b11 '
b10010000101010011010100100100 &
0%
1$
b100 #
0"
0!
$end
#100
b11000000100010010101111010000001 &
b11000000100010010101111010000001 5
b11000000100010010101111010000001 )
b11000000100010010101111010000001 1
1.
#150
10
#200
0.
#300
b10000100100001001101011000001001 &
b10000100100001001101011000001001 5
b10000100100001001101011000001001 )
b10000100100001001101011000001001 1
1.
#400
0.
#500
b10110001111100000101011001100011 &
b10110001111100000101011001100011 5
b10110001111100000101011001100011 )
b10110001111100000101011001100011 1
1.
#600
0.
#700
1"
b110101110010111101100001101 &
b110101110010111101100001101 5
b110101110010111101100001101 )
b110101110010111101100001101 1
b0 '
b0 4
b0 +
b0 2
1.
#800
0.
#900
b1000110110111111001100110001101 &
b1000110110111111001100110001101 5
b1000110110111111001100110001101 )
b1000110110111111001100110001101 1
1.
#1000
0.
#1100
1(
b10110010110000101000010001100101 &
b10110010110000101000010001100101 5
b10110010110000101000010001100101 )
b10110010110000101000010001100101 1
1/
1.
#1200
0.
#1300
0(
0"
1!
0$
b10001001001101110101001000010010 &
b10001001001101110101001000010010 5
b10001001001101110101001000010010 )
b10001001001101110101001000010010 1
1.
#1400
0.
#1500
0!
b111100111110001100000001 &
b111100111110001100000001 5
b111100111110001100000001 )
b111100111110001100000001 1
0/
1.
#1600
0.
#1700
b110110101111100110100001101 &
b110110101111100110100001101 5
b110110101111100110100001101 )
b110110101111100110100001101 1
1.
#1800
0.
#1900
b111011001000111111000101110110 &
b111011001000111111000101110110 5
b111011001000111111000101110110 )
b111011001000111111000101110110 1
1%
1*
1.
#2000
0.
#2100
16
0%
0*
b11110100011011100110100111101 &
b11110100011011100110100111101 5
b11110100011011100110100111101 )
b11110100011011100110100111101 1
1.
#2200
0.
#2300
1"
06
1$
b1110110110101000101011111101101 &
b1110110110101000101011111101101 5
b1110110110101000101011111101101 )
b1110110110101000101011111101101 1
1.
#2400
0.
#2500
b1000110001011011111011110001100 &
b1000110001011011111011110001100 5
b1000110001011011111011110001100 )
b1000110001011011111011110001100 1
1.
#2600
0.
#2700
b1111100111111011110100111111001 &
b1111100111111011110100111111001 5
b1111100111111011110100111111001 )
b1111100111111011110100111111001 1
1.
#2800
0.
#2900
b11100011001101110010010011000110 &
b11100011001101110010010011000110 5
b11100011001101110010010011000110 )
b11100011001101110010010011000110 1
1.
#3000
0.
#3100
b11100010111101111000010011000101 &
b11100010111101111000010011000101 5
b11100010111101111000010011000101 )
b11100010111101111000010011000101 1
1.
#3200
0.
#3300
b11010101000100111101001010101010 &
b11010101000100111101001010101010 5
b11010101000100111101001010101010 )
b11010101000100111101001010101010 1
1.
#3400
0.
#3500
b1110010101011111111011111100101 &
b1110010101011111111011111100101 5
b1110010101011111111011111100101 )
b1110010101011111111011111100101 1
1.
#3600
0.
#3700
b10111011110100100111001001110111 &
b10111011110100100111001001110111 5
b10111011110100100111001001110111 )
b10111011110100100111001001110111 1
1.
#3800
0.
#3900
b10001001001100101101011000010010 &
b10001001001100101101011000010010 5
b10001001001100101101011000010010 )
b10001001001100101101011000010010 1
1.
#4000
0.
#4100
b1000111111011001101101110001111 &
b1000111111011001101101110001111 5
b1000111111011001101101110001111 )
b1000111111011001101101110001111 1
1.
#4200
0.
#4300
b1111001001100000110100111110010 &
b1111001001100000110100111110010 5
b1111001001100000110100111110010 )
b1111001001100000110100111110010 1
1.
#4400
0.
#4500
b11100111011101101001011011001110 &
b11100111011101101001011011001110 5
b11100111011101101001011011001110 )
b11100111011101101001011011001110 1
1.
#4600
0.
#4700
b11110100000000000111101011101000 &
b11110100000000000111101011101000 5
b11110100000000000111101011101000 )
b11110100000000000111101011101000 1
1.
#4800
0.
#4900
b11100010110010100100111011000101 &
b11100010110010100100111011000101 5
b11100010110010100100111011000101 )
b11100010110010100100111011000101 1
1.
#5000
0.
#5100
b101110010110000100100101011100 &
b101110010110000100100101011100 5
b101110010110000100100101011100 )
b101110010110000100100101011100 1
1.
#5200
0.
#5300
b11011110100011100010100010111101 &
b11011110100011100010100010111101 5
b11011110100011100010100010111101 )
b11011110100011100010100010111101 1
1.
#5400
0.
#5500
b10010110101010110101100000101101 &
b10010110101010110101100000101101 5
b10010110101010110101100000101101 )
b10010110101010110101100000101101 1
1.
#5600
0.
#5700
b10110010101001110010011001100101 &
b10110010101001110010011001100101 5
b10110010101001110010011001100101 )
b10110010101001110010011001100101 1
1.
#5800
0.
#5900
b10110001111011110110001001100011 &
b10110001111011110110001001100011 5
b10110001111011110110001001100011 )
b10110001111011110110001001100011 1
1.
#6000
0.
#6100
b101011100111000011100001010 &
b101011100111000011100001010 5
b101011100111000011100001010 )
b101011100111000011100001010 1
1.
#6200
0.
#6300
b11000000001110110010001010000000 &
b11000000001110110010001010000000 5
b11000000001110110010001010000000 )
b11000000001110110010001010000000 1
1.
#6400
0.
#6500
b10000011001000010000100100000 &
b10000011001000010000100100000 5
b10000011001000010000100100000 )
b10000011001000010000100100000 1
1.
#6600
0.
#6700
b1010101011110000100010110101010 &
b1010101011110000100010110101010 5
b1010101011110000100010110101010 )
b1010101011110000100010110101010 1
1.
#6800
0.
#6900
b11001110110011001100110010011101 &
b11001110110011001100110010011101 5
b11001110110011001100110010011101 )
b11001110110011001100110010011101 1
1.
