MCDF/formatter/seq_ref.v
/********<MCDF重要信号时序参考:sequence_reference>*********/
`timescale 1ns/100ps
module seq_ref;
reg             clk_i;
reg             rst_n;
reg             fmt_grant;
wire            a2sx_ack,
                f2a_ack;//这三个信号为同一个信号，持续至少一个时钟周期，在开始发送后可以降低
assign  f2a_ack=fmt_grant & fmt_req;
assign  a2sx_ack=fmt_grant & fmt_req;

reg             fmt_id_req;//formatter空闲时为高
reg     [1:0]   a2f_id;//就绪通道信号
reg     [31:0]  fmt_data;//送出数据
reg             fmt_strat,
                fmt_req,
                fmt_end;//!!!end的产生可能与i息息相关         
initial begin
        clk_i<=0;
        rst_n<=0;
        fmt_grant<=0;
        fmt_id_req<=0;//
        a2f_id<=2'b11;//
        fmt_data<=0;
        fmt_strat<=0;
        fmt_end<=0;
        fmt_req<=0;   
        $dumpfile("seq_ref.vcd");
        $dumpvars;
#15     rst_n<=1;
@(posedge clk_i)    fmt_id_req<=1;
#40//等待下级就绪
@(posedge clk_i)    begin
    a2f_id<=2'b10;
    fmt_req<=1'b1;//表示就绪，等待grant
end 
#30
@(posedge clk_i)    fmt_grant<=1;
@(posedge clk_i)    begin
    fmt_req<=0;
    fmt_data<=$random;
    fmt_strat<=1;
    fmt_id_req<=0;    
end
@(posedge clk_i)begin
                    fmt_grant<=0;
                    fmt_data<=$random;
                    fmt_strat<=0;
end
@(posedge clk_i)begin
                    fmt_strat<=0;
                    fmt_data<=$random;
end

@(posedge clk_i)begin
    fmt_end<=1;
    fmt_data<=$random;
end
@(posedge clk_i)begin
    fmt_end<=0;
    fmt_data<=$random;
end

#500    $finish;
end
always #10 clk_i=~clk_i;
endmodule

MCDF/formatter/seq_ref.vcd
$date
	Tue Dec  6 19:49:37 2022
$end
$version
	Icarus Verilog
$end
$timescale
	100ps
$end
$scope module seq_ref $end
$var wire 1 ! a2sx_ack $end
$var wire 1 " f2a_ack $end
$var reg 2 # a2f_id [1:0] $end
$var reg 1 $ clk_i $end
$var reg 32 % fmt_data [31:0] $end
$var reg 1 & fmt_end $end
$var reg 1 ' fmt_grant $end
$var reg 1 ( fmt_id_req $end
$var reg 1 ) fmt_req $end
$var reg 1 * fmt_strat $end
$var reg 1 + rst_n $end
$upscope $end
$enddefinitions $end
#0
$dumpvars
0+
0*
0)
0(
0'
0&
b0 %
0$
b11 #
0"
0!
$end
#100
1$
#150
1+
#200
0$
#300
1(
1$
#400
0$
#500
1$
#600
0$
#700
1)
b10 #
1$
#800
0$
#900
1$
#1000
0$
#1100
1!
1"
1'
1$
#1200
0$
#1300
0!
0"
0(
1*
b10010000101010011010100100100 %
0)
1$
#1400
0$
#1500
0*
b11000000100010010101111010000001 %
0'
1$
#1600
0$
#1700
b10000100100001001101011000001001 %
1$
#1800
0$
#1900
b10110001111100000101011001100011 %
1&
1$
#2000
0$
#2100
b110101110010111101100001101 %
0&
1$
