同步FIFO/memory.v
`timescale 1ns/100ps
module memory #( 
    parameter   W = 8,//位宽
                L = 5//地址线
    ) (
    input  wire 	        clk, 
    input  wire [W-1 : 0]   data_A, //写数据
    input  wire [L-1 : 0]   addr_A, 
    output wire [W-1 : 0]   data_B, //读数据
    input  wire [L-1 : 0]   addr_B, 
    input  wire 	        rd,     //读信号，低有效
		                    wr      //写信号，低有效
    ); 
    reg [W-1 : 0] mem [(1<<L)-1 : 0]; //存储单元
    reg [L-1 : 0] addr_rd;
    assign data_B = mem[addr_rd];   //注意，因为data_B是wire类型，所以用addr_rd作为中间变量
    
    always @( posedge clk) 
        if(!rd)
            addr_rd <= addr_B;      //同步读

    always @( posedge clk)          //同步写
        if(!wr)
            mem[addr_A] <= data_A; 
endmodule

同步FIFO/SCFIFO.v
`timescale 1ns/100ps
`include "memory.v"
module  SCFIFO
#(
    parameter   W=4,//位宽
                L=4//地址
)
(
    input   clk,
            reset_n,
    input   wire [W-1:0] data_in,
    input   rd,
            wr,
    output  wire [W-1:0] data_out,
    output  full,
            empty            
);
reg    [L:0]       rd_addr;
reg    [L:0]       wr_addr;
wire    [L-1:0]     rd_addr_true;
wire    [L-1:0]     wr_addr_true;
wire    rd_addr_msb;
wire    wr_addr_msb;
wire    [3:0]   NULL_port;
assign  {rd_addr_msb,rd_addr_true}=rd_addr;
assign  {wr_addr_msb,wr_addr_true}=wr_addr;

memory memory1
(
    .clk(clk), 
    .data_A({4'b0,data_in}), //写数据
    .addr_A({1'b0,wr_addr_true}), 
    
    .data_B({NULL_port,data_out}), //读数据
    .addr_B({1'b0,rd_addr_true}), 
    .rd(rd),     //读信号，低有效
	.wr(rd)      //写信号，低有效
);
always @(posedge clk or negedge reset_n) begin//读
    if(~reset_n)
        rd_addr<='b0;
    else if(~rd&&~empty)begin//可读
        rd_addr<=rd_addr+1'b1;
    end   
end
always @(posedge clk or negedge reset_n) begin//写
    if(~reset_n)
        wr_addr<='b0;
    else if(~wr&&~full)begin//可写
        wr_addr<=wr_addr+1'b1;
    end    
end
assign empty=((rd_addr_msb==wr_addr_msb) && (rd_addr_true+'d4 > wr_addr_true))?1'b1:1'b0;//读空
assign full=((rd_addr_msb!=wr_addr_msb) && (rd_addr_true + 'd11 < wr_addr_true))?1'b1:1'b0;//写满
endmodule

同步FIFO/SCFIFO_tb.v
`timescale 1ns/1ns
`include "SCFIFO.v"
module SCFIFO_tb;
//************<端口声明>****************
reg             clk,
                reset_n;
reg     [3:0] data_in;
reg             rd,
                wr;
wire    [3:0] data_out;
wire            full,
                empty;   
//***********<模块例化>******************
SCFIFO FIFO1
(
    .clk(clk),
    .reset_n(reset_n),
    .data_in(data_in),
    .rd(rd),
    .wr(wr),

    .data_out(data_out),
    .full(full),
    .empty(empty)
);
initial begin
    $dumpfile("SCFIFO.vcd");
    $dumpvars;
    reset_n<=0;
    clk<=0;
    data_in='b0;
    rd<=0;
    wr<=0;
    #35 reset_n<=1'b1;
    repeat(32)begin
      @(negedge clk)
      begin
        rd<=0;
        wr<=0;
        data_in<=$random;
      end
    end
    #1000 $finish;
end
initial begin
  repeat(64)
    #10 clk<=~clk;
end

endmodule

同步FIFO/SCFIFO.vcd
$date
	Tue Nov 22 13:16:47 2022
$end
$version
	Icarus Verilog
$end
$timescale
	100ps
$end
$scope module SCFIFO_tb $end
$var wire 1 ! full $end
$var wire 1 " empty $end
$var wire 4 # data_out [3:0] $end
$var reg 1 $ clk $end
$var reg 4 % data_in [3:0] $end
$var reg 1 & rd $end
$var reg 1 ' reset_n $end
$var reg 1 ( wr $end
$scope module FIFO1 $end
$var wire 1 $ clk $end
$var wire 4 ) data_in [3:0] $end
$var wire 1 & rd $end
$var wire 1 ' reset_n $end
$var wire 1 ( wr $end
$var wire 4 * wr_addr_true [3:0] $end
$var wire 1 + wr_addr_msb $end
$var wire 4 , rd_addr_true [3:0] $end
$var wire 1 - rd_addr_msb $end
$var wire 1 ! full $end
$var wire 1 " empty $end
$var wire 4 . data_out [3:0] $end
$var wire 4 / NULL_port [3:0] $end
$var parameter 32 0 L $end
$var parameter 32 1 W $end
$var reg 5 2 rd_addr [4:0] $end
$var reg 5 3 wr_addr [4:0] $end
$scope module memory1 $end
$var wire 5 4 addr_A [4:0] $end
$var wire 5 5 addr_B [4:0] $end
$var wire 1 $ clk $end
$var wire 8 6 data_A [7:0] $end
$var wire 8 7 data_B [7:0] $end
$var wire 1 & rd $end
$var wire 1 & wr $end
$var parameter 32 8 L $end
$var parameter 32 9 W $end
$var reg 5 : addr_rd [4:0] $end
$upscope $end
$upscope $end
$upscope $end
$enddefinitions $end
$comment Show the parameter values. $end
$dumpall
b1000 9
b101 8
b100 1
b100 0
$end
#0
$dumpvars
bx :
bx 7
b0 6
b0 5
b0 4
b0 3
b0 2
bx /
bx .
0-
b0 ,
0+
b0 *
b0 )
0(
0'
0&
b0 %
0$
bx #
1"
0!
$end
#100
b0 #
b0 .
b0 /
b0 7
b0 :
1$
#200
0$
#300
1$
#350
1'
#400
b100 6
b100 %
b100 )
0$
#500
b100 #
b100 .
b1 4
b1 *
b100 7
b1 3
1$
#600
b1 6
b1 %
b1 )
0$
#700
b10 4
b10 *
b10 3
1$
#800
b1001 6
b1001 %
b1001 )
0$
#900
b11 4
b11 *
b11 3
1$
#1000
b11 6
b11 %
b11 )
0$
#1100
0"
b100 4
b100 *
b100 3
1$
#1200
b1101 6
b1101 %
b1101 )
0$
#1300
b101 4
b101 *
b1 5
b1 ,
b101 3
b1 2
1$
#1400
0$
#1500
b1 #
b1 .
b10 5
b10 ,
b110 4
b110 *
b1 7
b1 :
b10 2
b110 3
1$
#1600
b101 6
b101 %
b101 )
0$
#1700
b1001 #
b1001 .
b111 4
b111 *
b11 5
b11 ,
b1001 7
b10 :
b111 3
b11 2
1$
#1800
b10 6
b10 %
b10 )
0$
#1900
b11 #
b11 .
b100 5
b100 ,
b1000 4
b1000 *
b11 7
b11 :
b100 2
b1000 3
1$
#2000
b1 6
b1 %
b1 )
0$
#2100
b1101 #
b1101 .
b1001 4
b1001 *
b101 5
b101 ,
b1101 7
b100 :
b1001 3
b101 2
1$
#2200
b1101 6
b1101 %
b1101 )
0$
#2300
b110 5
b110 ,
b1010 4
b1010 *
b101 :
b110 2
b1010 3
1$
#2400
b110 6
b110 %
b110 )
0$
#2500
b101 #
b101 .
b1011 4
b1011 *
b111 5
b111 ,
b101 7
b110 :
b1011 3
b111 2
1$
#2600
b1101 6
b1101 %
b1101 )
0$
#2700
b10 #
b10 .
b1000 5
b1000 ,
b1100 4
b1100 *
b10 7
b111 :
b1000 2
b1100 3
1$
#2800
0$
#2900
b1 #
b1 .
b1101 4
b1101 *
b1001 5
b1001 ,
b1 7
b1000 :
b1101 3
b1001 2
1$
#3000
b1100 6
b1100 %
b1100 )
0$
#3100
b1101 #
b1101 .
b1010 5
b1010 ,
b1110 4
b1110 *
b1101 7
b1001 :
b1010 2
b1110 3
1$
#3200
b1001 6
b1001 %
b1001 )
0$
#3300
b110 #
b110 .
b1111 4
b1111 *
b1011 5
b1011 ,
b110 7
b1010 :
b1111 3
b1011 2
1$
#3400
b110 6
b110 %
b110 )
0$
#3500
0"
b1101 #
b1101 .
b1100 5
b1100 ,
1+
b0 4
b0 *
b1101 7
b1011 :
b1100 2
b10000 3
1$
#3600
b101 6
b101 %
b101 )
0$
#3700
b1 4
b1 *
b1101 5
b1101 ,
b1100 :
b10001 3
b1101 2
1$
#3800
b1010 6
b1010 %
b1010 )
0$
#3900
b1100 #
b1100 .
b1110 5
b1110 ,
b10 4
b10 *
b1100 7
b1101 :
b1110 2
b10010 3
1$
#4000
b101 6
b101 %
b101 )
0$
#4100
b1001 #
b1001 .
b11 4
b11 *
b1111 5
b1111 ,
b1001 7
b1110 :
b10011 3
b1111 2
1$
#4200
b111 6
b111 %
b111 )
0$
#4300
b110 #
b110 .
1-
b0 5
b0 ,
b100 4
b100 *
b110 7
b1111 :
b10000 2
b10100 3
1$
#4400
b10 6
b10 %
b10 )
0$
#4500
b101 #
b101 .
b101 4
b101 *
b1 5
b1 ,
b101 7
b0 :
b10101 3
b10001 2
1$
#4600
b1111 6
b1111 %
b1111 )
0$
#4700
b1010 #
b1010 .
b10 5
b10 ,
b110 4
b110 *
b1010 7
b1 :
b10010 2
b10110 3
1$
#4800
b10 6
b10 %
b10 )
0$
#4900
b101 #
b101 .
b111 4
b111 *
b11 5
b11 ,
b101 7
b10 :
b10111 3
b10011 2
1$
#5000
b1110 6
b1110 %
b1110 )
0$
#5100
b111 #
b111 .
b100 5
b100 ,
b1000 4
b1000 *
b111 7
b11 :
b10100 2
b11000 3
1$
#5200
b1000 6
b1000 %
b1000 )
0$
#5300
b10 #
b10 .
b1001 4
b1001 *
b101 5
b101 ,
b10 7
b100 :
b11001 3
b10101 2
1$
#5400
b101 6
b101 %
b101 )
0$
#5500
b1111 #
b1111 .
b110 5
b110 ,
b1010 4
b1010 *
b1111 7
b101 :
b10110 2
b11010 3
1$
#5600
b1100 6
b1100 %
b1100 )
0$
#5700
b10 #
b10 .
b1011 4
b1011 *
b111 5
b111 ,
b10 7
b110 :
b11011 3
b10111 2
1$
#5800
b1101 6
b1101 %
b1101 )
0$
#5900
b1110 #
b1110 .
b1000 5
b1000 ,
b1100 4
b1100 *
b1110 7
b111 :
b11000 2
b11100 3
1$
#6000
0$
#6100
b1000 #
b1000 .
b1101 4
b1101 *
b1001 5
b1001 ,
b1000 7
b1000 :
b11101 3
b11001 2
1$
#6200
b101 6
b101 %
b101 )
0$
#6300
b101 #
b101 .
b1010 5
b1010 ,
b1110 4
b1110 *
b101 7
b1001 :
b11010 2
b11110 3
1$
#6400
b11 6
b11 %
b11 )
0$
