MCDF/arbiter/arbiter.v
/*************************<MCDF仲裁器>*********************/
`timescale 1ns/100ps
/*************************<端口声明>*********************/
module arbiter
(
//Input
    input   wire            clk_i,
                            rstn_i,
/*******************<control register 接口>*******/
    input   wire    [1:0]   slv0_prio_i,
                            slv1_prio_i,
                            slv2_prio_i,
    input   wire    [2:0]   slv0_pkglen_i,
                            slv1_pkglen_i,
                            slv2_pkglen_i,
/*******************<slave 接口>*********************/
    input   wire    [31:0]  slv0_data_i,
                            slv1_data_i,
                            slv2_data_i,
    input   wire            slv0_req_i,
                            slv1_req_i,
                            slv2_req_i,    
                            slv0_val_i,
                            slv1_val_i,
                            slv2_val_i,
/*******************<formatter 接口>*********************/    
    input   wire            f2a_id_req_i,       //formatter请求接收
                            f2a_ack_i,
//Output
/*******************<slave 接口>*********************/    
    output  reg             a2s0_ack_o,         //[-slv]f2a_ack_i
                            a2s1_ack_o,
                            a2s2_ack_o,
/*******************<formatter 接口>*********************/
                            a2f_val_o,          //[-slv]slvx_val_i,包有效包络信号
    output  reg     [1:0]   a2f_id_o,           //通道编号
    output  reg     [31:0]  a2f_data_o,         //[-slv]slvx_data_i
    output  reg     [2:0]   a2f_pkglen_sel_o    //[-slv]slvx_pkglen_i
);
/*****************<中间信号>*********************/
wire    [3:0]   ch0_prio_syn,//各通道综合优先级，计算方法见下
                ch1_prio_syn,
                ch2_prio_syn;
reg     [5:0]   channel_prio;//通道优先级综合排序寄存器[5:4最高优先级通道序号][3：2次高优先级通道序号][1：0最低优先级通道序号]
wire    [2:0]   slvx_req;//输入请求集中,!!!写成向量比数组更好，向量可以查看值，防止出错
assign  slvx_req[0]=slv0_req_i;
assign  slvx_req[1]=slv1_req_i;
assign  slvx_req[2]=slv2_req_i;
/*****************<综合优先级生成电路：组合逻辑>*********************/
assign ch0_prio_syn=({2'b0,slv0_prio_i}<<2)+'d0;//[3:2是设置prio][1：0是自有prio，3：2相等时才起作用]
assign ch1_prio_syn=({2'b0,slv1_prio_i}<<2)+'d1;
assign ch2_prio_syn=({2'b0,slv2_prio_i}<<2)+'d2;
/*****************<优先级整合逻辑>*********************/
//根据综合优先级得出最优先通道（数值最小）
always @(*) begin//综合优先级生成电路保证不可能相等
    if(ch0_prio_syn>ch1_prio_syn)begin
        if(ch1_prio_syn>ch2_prio_syn)
            channel_prio<=6'b10_01_00;
        else begin
            if(ch0_prio_syn>ch2_prio_syn)
                channel_prio<=6'b01_10_00;
            else
                channel_prio<=6'b01_00_10;
        end
    end
    else begin
        if(ch1_prio_syn<ch2_prio_syn)
            channel_prio<=6'b00_01_10;
        else begin
            if(ch0_prio_syn<ch2_prio_syn)
                channel_prio<=6'b00_10_01;
            else
                channel_prio<=6'b10_00_01;
        end        
    end
end
/*****************<时序电路>*********************/
//用于产生仲裁信号 a2f_id_o !!!如果都没准备号，就发送11
always @(posedge clk_i or negedge rstn_i) begin
    if(~rstn_i)begin//输出全部置0
        a2f_id_o<=2'b11;//进入default间接置0
    end
    else if(f2a_id_req_i)begin//当上级(formatter)命令可以发送包!!!f2a_id_req_i应当时单周期信号，不能持续
        if(slvx_req[channel_prio[5:4]])//先查看优先级最高的slave是否请求发送
            a2f_id_o<=channel_prio[5:4];
        else if(slvx_req[channel_prio[3:2]])
            a2f_id_o<=channel_prio[3:2];
        else if(slvx_req[channel_prio[1:0]])
            a2f_id_o<=channel_prio[1:0];
        else
            a2f_id_o<=2'b11;
    end
    else
        a2f_id_o<=a2f_id_o;
end

/*****************<多路选择器部分>*********************/
always @(*) begin
    case(a2f_id_o)
    2'b00:begin
        a2f_val_o=slv0_val_i;
        a2f_data_o=slv0_data_i;  
        a2f_pkglen_sel_o=slv0_pkglen_i;
        
        a2s0_ack_o=f2a_ack_i;
        a2s1_ack_o=0;
        a2s2_ack_o=0;
    end

    2'b01:begin
        a2f_val_o=slv1_val_i;
        a2f_data_o=slv1_data_i; 
        a2f_pkglen_sel_o=slv1_pkglen_i; 
        
        a2s0_ack_o=0;
        a2s1_ack_o=f2a_ack_i;
        a2s2_ack_o=0;
    end

    2'b10:begin
        a2f_val_o=slv2_val_i;
        a2f_data_o=slv2_data_i; 
        a2f_pkglen_sel_o=slv2_pkglen_i;
        
        a2s0_ack_o=0;
        a2s1_ack_o=0;
        a2s2_ack_o=f2a_ack_i;
    end

    2'b11:begin//default
        a2f_val_o=0;
        a2f_data_o=0; 
        a2f_pkglen_sel_o=0;
        
        a2s0_ack_o=0;
        a2s1_ack_o=0;
        a2s2_ack_o=0;
    end
    endcase
end
endmodule

MCDF/arbiter/arbiter_tb.v
`timescale 1ns/1ns
`include "arbiter.v"
/*************************<端口声明>*********************/
module arbiter_tb;
reg             clk_i,
                rstn_i;
/********<control register 接口>*******/
reg     [1:0]   slv0_prio_i,
                slv1_prio_i,
                slv2_prio_i;
reg     [2:0]   slv0_pkglen_i,
                slv1_pkglen_i,
                slv2_pkglen_i;
/********<slave 接口>*********************/
reg     [31:0]  slv0_data_i,
                slv1_data_i,
                slv2_data_i;
reg             slv0_req_i,
                slv1_req_i,
                slv2_req_i,    
                slv0_val_i,
                slv1_val_i,
                slv2_val_i;
/********<formatter 接口>*********************/    
reg             f2a_id_req_i,       //formatter请求接收
                f2a_ack_i;
/********<slave 接口>*********************/    
wire            a2s0_ack_o,         //[-slv]f2a_ack_i
                a2s1_ack_o,
                a2s2_ack_o,
/********<formatter 接口>*********************/
                a2f_val_o;         //[-slv]slvx_val_i,包有效包络信号
wire    [1:0]   a2f_id_o;           //通道编号
wire    [31:0]  a2f_data_o;         //[-slv]slvx_data_i
wire    [2:0]   a2f_pkglen_sel_o;    //[-slv]slvx_pkglen_i

/********************<实例化arbiter>*********************/
arbiter ar1(
    clk_i,
    rstn_i,

    slv0_prio_i,
    slv1_prio_i,
    slv2_prio_i,
    slv0_pkglen_i,
    slv1_pkglen_i,
    slv2_pkglen_i,

    slv0_data_i,
    slv1_data_i,
    slv2_data_i,
    slv0_req_i,
    slv1_req_i,
    slv2_req_i,    
    slv0_val_i,
    slv1_val_i,
    slv2_val_i,

    f2a_id_req_i,   
    f2a_ack_i,

    a2s0_ack_o,     
    a2s1_ack_o,
    a2s2_ack_o,

    a2f_val_o,     
    a2f_id_o,       
    a2f_data_o,     
    a2f_pkglen_sel_o
);
initial begin
/*********<初始化>**********/
    clk_i<=0;
    rstn_i<=0;//

    slv0_prio_i<=2'b11;//
    slv1_prio_i<=2'b01;//这个是最优先通道
    slv2_prio_i<=2'b01;//次优先通道
    slv0_pkglen_i<=2'b10;//
    slv1_pkglen_i<=2'b01;//数据长8
    slv2_pkglen_i<=2'b00;//数据长4

    slv0_data_i<=$random;
    slv1_data_i<=$random;
    slv2_data_i<=$random;
    slv0_req_i<=0;
    slv1_req_i<=0;
    slv2_req_i<=0; 
    slv0_val_i<=0;
    slv1_val_i<=0;
    slv2_val_i<=0;

    f2a_id_req_i<=0;//短时信号，在slvx_req_i就绪之后  
    f2a_ack_i<=0;//在slvx_req_i就绪之后
    $dumpfile("arbiter.vcd");
    $dumpvars;
/*********<生成波形>**********/
#25     rstn_i<=1;
#20     slv0_req_i<=1;
        slv1_req_i<=1;
        slv2_req_i<=1;
@(posedge clk_i)begin
    f2a_id_req_i<=1;//两个短时信号
end 
@(posedge clk_i)begin
    f2a_id_req_i<=0;
    f2a_ack_i<=1;     
end
@(posedge clk_i)begin
    f2a_ack_i<=0;     
end
 
        repeat(8)begin
            @(posedge clk_i)begin
                slv0_data_i<=$random;
                slv1_data_i<=$random;
                slv2_data_i<=$random;
                slv0_val_i<=0;
                slv1_val_i<=1;
                slv2_val_i<=0;                
            end
        end
@(posedge clk_i)begin
    slv0_data_i<=$random;
    slv1_data_i<=$random;
    slv2_data_i<=$random;
    slv0_val_i<=0;
    slv1_val_i<=0;
    slv2_val_i<=0;
    slv0_req_i<=0;
    slv1_req_i<=0;
    slv2_req_i<=0;                
end
#2000   $finish;
end
always #10 clk_i<=~clk_i;
endmodule

MCDF/arbiter/arbiter.vcd
$date
	Mon Dec  5 20:00:16 2022
$end
$version
	Icarus Verilog
$end
$timescale
	100ps
$end
$scope module arbiter_tb $end
$var wire 1 ! a2s2_ack_o $end
$var wire 1 " a2s1_ack_o $end
$var wire 1 # a2s0_ack_o $end
$var wire 1 $ a2f_val_o $end
$var wire 3 % a2f_pkglen_sel_o [2:0] $end
$var wire 2 & a2f_id_o [1:0] $end
$var wire 32 ' a2f_data_o [31:0] $end
$var reg 1 ( clk_i $end
$var reg 1 ) f2a_ack_i $end
$var reg 1 * f2a_id_req_i $end
$var reg 1 + rstn_i $end
$var reg 32 , slv0_data_i [31:0] $end
$var reg 3 - slv0_pkglen_i [2:0] $end
$var reg 2 . slv0_prio_i [1:0] $end
$var reg 1 / slv0_req_i $end
$var reg 1 0 slv0_val_i $end
$var reg 32 1 slv1_data_i [31:0] $end
$var reg 3 2 slv1_pkglen_i [2:0] $end
$var reg 2 3 slv1_prio_i [1:0] $end
$var reg 1 4 slv1_req_i $end
$var reg 1 5 slv1_val_i $end
$var reg 32 6 slv2_data_i [31:0] $end
$var reg 3 7 slv2_pkglen_i [2:0] $end
$var reg 2 8 slv2_prio_i [1:0] $end
$var reg 1 9 slv2_req_i $end
$var reg 1 : slv2_val_i $end
$scope module ar1 $end
$var wire 1 ( clk_i $end
$var wire 1 ) f2a_ack_i $end
$var wire 1 * f2a_id_req_i $end
$var wire 1 + rstn_i $end
$var wire 32 ; slv0_data_i [31:0] $end
$var wire 3 < slv0_pkglen_i [2:0] $end
$var wire 2 = slv0_prio_i [1:0] $end
$var wire 1 / slv0_req_i $end
$var wire 1 0 slv0_val_i $end
$var wire 32 > slv1_data_i [31:0] $end
$var wire 3 ? slv1_pkglen_i [2:0] $end
$var wire 2 @ slv1_prio_i [1:0] $end
$var wire 1 4 slv1_req_i $end
$var wire 1 5 slv1_val_i $end
$var wire 32 A slv2_data_i [31:0] $end
$var wire 3 B slv2_pkglen_i [2:0] $end
$var wire 2 C slv2_prio_i [1:0] $end
$var wire 1 9 slv2_req_i $end
$var wire 1 : slv2_val_i $end
$var wire 3 D slvx_req [2:0] $end
$var wire 4 E ch2_prio_syn [3:0] $end
$var wire 4 F ch1_prio_syn [3:0] $end
$var wire 4 G ch0_prio_syn [3:0] $end
$var reg 32 H a2f_data_o [31:0] $end
$var reg 2 I a2f_id_o [1:0] $end
$var reg 3 J a2f_pkglen_sel_o [2:0] $end
$var reg 1 $ a2f_val_o $end
$var reg 1 # a2s0_ack_o $end
$var reg 1 " a2s1_ack_o $end
$var reg 1 ! a2s2_ack_o $end
$var reg 6 K channel_prio [5:0] $end
$upscope $end
$upscope $end
$enddefinitions $end
#0
$dumpvars
b11000 K
b0 J
b11 I
b0 H
b1100 G
b101 F
b110 E
b0 D
b1 C
b0 B
b10000100100001001101011000001001 A
b1 @
b1 ?
b11000000100010010101111010000001 >
b11 =
b10 <
b10010000101010011010100100100 ;
0:
09
b1 8
b0 7
b10000100100001001101011000001001 6
05
04
b1 3
b1 2
b11000000100010010101111010000001 1
00
0/
b11 .
b10 -
b10010000101010011010100100100 ,
0+
0*
0)
0(
b0 '
b11 &
b0 %
0$
0#
0"
0!
$end
#100
1(
#200
0(
#250
1+
#300
1(
#400
0(
#450
19
14
b111 D
1/
#500
1*
1(
#600
0(
#700
1"
b1 %
b1 J
b11000000100010010101111010000001 '
b11000000100010010101111010000001 H
b1 &
b1 I
1)
0*
1(
#800
0(
#900
0"
0)
1(
#1000
0(
#1100
b110101110010111101100001101 '
b110101110010111101100001101 H
1$
15
b1000110110111111001100110001101 6
b1000110110111111001100110001101 A
b110101110010111101100001101 1
b110101110010111101100001101 >
b10110001111100000101011001100011 ,
b10110001111100000101011001100011 ;
1(
#1200
0(
#1300
b10001001001101110101001000010010 '
b10001001001101110101001000010010 H
b111100111110001100000001 6
b111100111110001100000001 A
b10001001001101110101001000010010 1
b10001001001101110101001000010010 >
b10110010110000101000010001100101 ,
b10110010110000101000010001100101 ;
1(
#1400
0(
#1500
b111011001000111111000101110110 '
b111011001000111111000101110110 H
b11110100011011100110100111101 6
b11110100011011100110100111101 A
b111011001000111111000101110110 1
b111011001000111111000101110110 >
b110110101111100110100001101 ,
b110110101111100110100001101 ;
1(
#1600
0(
#1700
b1000110001011011111011110001100 '
b1000110001011011111011110001100 H
b1111100111111011110100111111001 6
b1111100111111011110100111111001 A
b1000110001011011111011110001100 1
b1000110001011011111011110001100 >
b1110110110101000101011111101101 ,
b1110110110101000101011111101101 ;
1(
#1800
0(
#1900
b11100010111101111000010011000101 '
b11100010111101111000010011000101 H
b11010101000100111101001010101010 6
b11010101000100111101001010101010 A
b11100010111101111000010011000101 1
b11100010111101111000010011000101 >
b11100011001101110010010011000110 ,
b11100011001101110010010011000110 ;
1(
#2000
0(
#2100
b10111011110100100111001001110111 '
b10111011110100100111001001110111 H
b10001001001100101101011000010010 6
b10001001001100101101011000010010 A
b10111011110100100111001001110111 1
b10111011110100100111001001110111 >
b1110010101011111111011111100101 ,
b1110010101011111111011111100101 ;
1(
#2200
0(
#2300
b1111001001100000110100111110010 '
b1111001001100000110100111110010 H
b11100111011101101001011011001110 6
b11100111011101101001011011001110 A
b1111001001100000110100111110010 1
b1111001001100000110100111110010 >
b1000111111011001101101110001111 ,
b1000111111011001101101110001111 ;
1(
#2400
0(
#2500
b11100010110010100100111011000101 '
b11100010110010100100111011000101 H
b101110010110000100100101011100 6
b101110010110000100100101011100 A
b11100010110010100100111011000101 1
b11100010110010100100111011000101 >
b11110100000000000111101011101000 ,
b11110100000000000111101011101000 ;
1(
#2600
0(
#2700
b10010110101010110101100000101101 '
b10010110101010110101100000101101 H
0$
09
04
b0 D
0/
05
b10110010101001110010011001100101 6
b10110010101001110010011001100101 A
b10010110101010110101100000101101 1
b10010110101010110101100000101101 >
b11011110100011100010100010111101 ,
b11011110100011100010100010111101 ;
1(
