常见数字电路/十进制计数器/cnt10.v
//计数溢出后自动复位的十进制计数器
module cnt10(
    input               clk ,
    input               clr ,   //清零信号
    input               en  ,   //计数使能
    output              c   ,   //溢出标志
    output  reg[3:0]    out     //计数输出
);
always @(posedge clk,negedge clr) begin
    if(~clr)
        out<=4'b0;
    else if(en)
        if(out>=4'd9)
            out<=4'b0;//如果不自动复位，out<=4'd9
        else
            out<=out+1;
    else
        out<=out;    
end
assign c=out[3] & out[0];
endmodule

常见数字电路/十进制计数器/cnt10_tb.v
`timescale 1ns/100ps
`include "cnt10.v"
module  cnt10_tb;
reg              clk ;
reg              clr ;   //清零信号
reg              en  ;   //计数使能
wire             c   ;   //溢出标志
wire[3:0]        out ;    //计数输出
//*********<模块例化>*************
cnt10 c1
(
    clk,
    clr,
    en,
    c,
    out
);
initial begin
    $dumpfile("cnt10.vcd");
    $dumpvars;
    clr<=0;
    clk<=0;
    en<=1;
    #25     clr<=1;
    #235    en<=0;
    #50    en<=1;
    #1000   $finish;
end
always #10
    clk<=~clk;
endmodule

常见数字电路/十进制计数器/cnt10.vcd
$date
	Thu Feb 23 11:14:50 2023
$end
$version
	Icarus Verilog
$end
$timescale
	100ps
$end
$scope module cnt10_tb $end
$var wire 4 ! out [3:0] $end
$var wire 1 " c $end
$var reg 1 # clk $end
$var reg 1 $ clr $end
$var reg 1 % en $end
$scope module c1 $end
$var wire 1 " c $end
$var wire 1 # clk $end
$var wire 1 $ clr $end
$var wire 1 % en $end
$var reg 4 & out [3:0] $end
$upscope $end
$upscope $end
$enddefinitions $end
$comment Show the parameter values. $end
$dumpall
$end
#0
$dumpvars
b0 &
1%
0$
0#
0"
b0 !
$end
#100
1#
#200
0#
#250
1$
#300
b1 !
b1 &
1#
#400
0#
#500
b10 !
b10 &
1#
#600
0#
#700
b11 !
b11 &
1#
#800
0#
#900
b100 !
b100 &
1#
#1000
0#
#1100
b101 !
b101 &
1#
#1200
0#
#1300
b110 !
b110 &
1#
#1400
0#
#1500
b111 !
b111 &
1#
#1600
0#
#1700
b1000 !
b1000 &
1#
#1800
0#
#1900
1"
b1001 !
b1001 &
1#
#2000
0#
#2100
0"
b0 !
b0 &
1#
#2200
0#
#2300
b1 !
b1 &
1#
#2400
0#
#2500
b10 !
b10 &
1#
#2600
0#
0%
#2700
1#
#2800
0#
#2900
1#
#3000
0#
#3100
b11 !
b11 &
1#
1%
#3200
0#
#3300
b100 !
b100 &
1#
#3400
0#
#3500
b101 !
b101 &
1#
#3600
0#
#3700
b110 !
b110 &
1#
#3800
0#
#3900
b111 !
b111 &
1#
#4000
0#
#4100
b1000 !
b1000 &
1#
#4200
0#
#4300
1"
b1001 !
b1001 &
1#
#4400
0#
#4500
0"
b0 !
b0 &
1#
#4600
0#
#4700
b1 !
b1 &
1#
#4800
0#
#4900
b10 !
b10 &
1#
#5000
0#
#5100
b11 !
b11 &
1#
#5200
0#
#5300
b100 !
b100 &
1#
#5400
0#
#5500
b101 !
b101 &
1#
#5600
0#
#5700
b110 !
b110 &
1#
#5800
0#
#5900
b111 !
b111 &
1#
#6000
0#
#6100
b1000 !
b1000 &
1#
#6200
0#
#6300
1"
b1001 !
b1001 &
1#
#6400
0#
#6500
0"
b0 !
b0 &
1#
#6600
0#
#6700
b1 !
b1 &
1#
#6800
0#
#6900
b10 !
b10 &
1#
#7000
0#
#7100
b11 !
b11 &
1#
#7200
0#
#7300
b100 !
b100 &
1#
#7400
0#
#7500
b101 !
b101 &
1#
#7600
0#
#7700
b110 !
b110 &
1#
#7800
0#
#7900
b111 !
b111 &
1#
#8000
0#
#8100
b1000 !
b1000 &
1#
#8200
0#
#8300
1"
b1001 !
b1001 &
1#
#8400
0#
#8500
0"
b0 !
b0 &
1#
#8600
0#
#8700
b1 !
b1 &
1#
#8800
0#
#8900
b10 !
b10 &
1#
#9000
0#
#9100
b11 !
b11 &
1#
#9200
0#
#9300
b100 !
b100 &
1#
#9400
0#
#9500
b101 !
b101 &
1#
#9600
0#
#9700
b110 !
b110 &
1#
#9800
0#
#9900
b111 !
b111 &
1#
#10000
0#
#10100
b1000 !
b1000 &
1#
#10200
0#
#10300
1"
b1001 !
b1001 &
1#
#10400
0#
#10500
0"
b0 !
b0 &
1#
#10600
0#
#10700
b1 !
b1 &
1#
#10800
0#
#10900
b10 !
b10 &
1#
#11000
0#
#11100
b11 !
b11 &
1#
#11200
0#
#11300
b100 !
b100 &
1#
#11400
0#
#11500
b101 !
b101 &
1#
#11600
0#
#11700
b110 !
b110 &
1#
#11800
0#
#11900
b111 !
b111 &
1#
#12000
0#
#12100
b1000 !
b1000 &
1#
#12200
0#
#12300
1"
b1001 !
b1001 &
1#
#12400
0#
#12500
0"
b0 !
b0 &
1#
#12600
0#
#12700
b1 !
b1 &
1#
#12800
0#
#12900
b10 !
b10 &
1#
#13000
0#
#13100
b11 !
b11 &
1#
