同步异步电路/控制信号的同步/f2s_control_2.v
/*参考刘清帆CSDN:【SOC架构】（一）同步与异步信号*/
/*快时钟域控制信号同步到慢时钟域*/
//方法2：停时钟法
module f2s_control(
    input       adat,
                rst,
                aclk,
                bclk,
    output  reg bdat
);
reg     adat1,
        bdat1,
        bdat2,
        bdat3,
        abdat1,
        abdat2,
        stall;
wire    aclk_gt;
//双向同步器
always @(posedge aclk or negedge rst) begin
    if(~rst)
        {abdat2,abdat1}<=2'b00;
    else
        {abdat2,abdat1}<={abdat1,bdat2};
end
always @(posedge bclk or negedge rst) begin
    if(~rst)
        {bdat2,bdat1}<=2'b00;
    else
        {bdat2,bdat1}<={bdat1,adat1};
end
//慢同步到快波形变化
always @(posedge bclk or negedge rst) begin
    if(~rst)
        bdat3<=2'b00;
    else
        bdat3<=bdat2;
end
always @(*) begin
        bdat<=({bdat3,bdat2}==2'b01)?1:0;
end
//反馈组合逻辑
assign aclk_gt=aclk & stall;
always@(*)begin
    if(abdat2==1)
        stall<=1'b1;//重启时钟
    else if(adat1==1)
        stall<=1'b0;//停时钟
    else
        stall<=1'b1;
end
always @(posedge aclk_gt or negedge rst) begin
    if(~rst)
        adat1<=1'b0;
    else
        adat1<=adat;
end

endmodule

同步异步电路/快时钟域控制信号同步到慢时钟域/f2s_control_2_tb.v
/*参考刘清帆CSDN:【SOC架构】（一）同步与异步信号*/
/*快时钟域控制信号同步到慢时钟域*/
/*测试*/
`timescale 1ns/1ns
`include "f2s_control_2.v"
module f2s_control_2_tb;
//************<端口声明>****************
reg         adat,
            rst,
            aclk,
            bclk;
wire        bdat;
//***********<模块例化>******************
f2s_control M1(
    adat,
    rst,
    aclk,
    bclk,
    bdat
);
initial begin
    $dumpfile("f2s_control_2.vcd");
    $dumpvars;
    aclk<=0;
    bclk<=0;
    rst<=0;
    adat<=0;
    #12 rst<=1;
    #20 @(posedge aclk)  adat<=1;
    @(posedge aclk)  adat<=0;
    #1000   $finish;
end
always #7 
    aclk<=~aclk;
always #10 
    bclk<=~bclk;
endmodule

同步异步电路/控制信号的同步/f2s_control_2.vcd
$date
	Thu Feb 09 23:30:19 2023
$end
$version
	Icarus Verilog
$end
$timescale
	1ns
$end
$scope module f2s_control_2_tb $end
$var wire 1 ! bdat $end
$var reg 1 " aclk $end
$var reg 1 # adat $end
$var reg 1 $ bclk $end
$var reg 1 % rst $end
$scope module M1 $end
$var wire 1 " aclk $end
$var wire 1 & aclk_gt $end
$var wire 1 # adat $end
$var wire 1 $ bclk $end
$var wire 1 % rst $end
$var reg 1 ' abdat1 $end
$var reg 1 ( abdat2 $end
$var reg 1 ) adat1 $end
$var reg 1 ! bdat $end
$var reg 1 * bdat1 $end
$var reg 1 + bdat2 $end
$var reg 1 , bdat3 $end
$var reg 1 - stall $end
$upscope $end
$upscope $end
$enddefinitions $end
$comment Show the parameter values. $end
$dumpall
$end
#0
$dumpvars
1-
0,
0+
0*
0)
0(
0'
0&
0%
0$
0#
0"
0!
$end
#7
1&
1"
#10
1$
#12
1%
#14
0&
0"
#20
0$
#21
1&
1"
#28
0&
0"
#30
1$
#35
1#
1&
1"
#40
0$
#42
0&
0"
#49
0-
1)
0#
0&
1"
#50
1*
1$
#56
0"
#60
0$
#63
1"
#70
1!
1+
0"
1$
#77
1'
1"
#80
0$
#84
0"
#90
0!
1,
1$
#91
0)
1&
1-
1(
1"
#98
0&
0"
#100
0$
#105
1&
1"
#110
0*
1$
#112
0&
0"
#119
1&
1"
#120
0$
#126
0&
0"
#130
0+
1$
#133
0'
1&
1"
#140
0&
0"
0$
#147
0(
1&
1"
#150
0,
1$
