常见数字电路/分频器/odd_division.v
module odd_division
#(
    parameter ODD_NUM=7
    )
(
    input clk_i,
    input rst_n,
    output clk_division
);

parameter BASE_NUM=(ODD_NUM-1)/2;
reg [9:0] pos_cnt;
reg [9:0] neg_cnt;

always@(posedge clk_i,negedge rst_n)begin
    if(~rst_n)
        pos_cnt<=0;
    else if(pos_cnt<ODD_NUM-1)
        pos_cnt<=pos_cnt+1;
    else
        pos_cnt<=0;
end

always@(negedge clk_i,negedge rst_n)begin
    if(~rst_n)
        neg_cnt<=0;
    else if(neg_cnt<ODD_NUM-1)
        neg_cnt<=neg_cnt+1;
    else
        neg_cnt<=0;
end

assign clk_division=((pos_cnt>BASE_NUM)||(neg_cnt>BASE_NUM));
endmodule

常见数字电路/分频器/odd_division_tb.v
`include "odd_division.v"
`timescale 1ns/1ps
module odd_division_tb;
reg    clk_i;
reg    rst_n;
wire   clk_division;

odd_division#(.ODD_NUM(7)) od1(
    clk_i,
    rst_n,
    clk_division
);
initial begin
    $dumpfile("odd_division.vcd");
    $dumpvars;
    rst_n<=0;
    clk_i<=0;
    #32     rst_n<=1;
    #1000 $finish;
end
always #5 clk_i=~clk_i;

endmodule

常见数字电路/分频器/odd_division.vcd
$date
	Thu Mar 23 00:34:31 2023
$end
$version
	Icarus Verilog
$end
$timescale
	1ps
$end
$scope module odd_division_tb $end
$var wire 1 ! clk_division $end
$var reg 1 " clk_i $end
$var reg 1 # rst_n $end
$scope module od1 $end
$var wire 1 ! clk_division $end
$var wire 1 " clk_i $end
$var wire 1 # rst_n $end
$var reg 10 $ neg_cnt [9:0] $end
$var reg 10 % pos_cnt [9:0] $end
$upscope $end
$upscope $end
$enddefinitions $end
#0
$dumpvars
b0 %
b0 $
0#
0"
0!
$end
#5000
1"
#10000
0"
#15000
1"
#20000
0"
#25000
1"
#30000
0"
#32000
1#
#35000
b1 %
1"
#40000
b1 $
0"
#45000
b10 %
1"
#50000
b10 $
0"
#55000
b11 %
1"
#60000
b11 $
0"
#65000
1!
b100 %
1"
#70000
b100 $
0"
#75000
b101 %
1"
#80000
b101 $
0"
#85000
b110 %
1"
#90000
b110 $
0"
#95000
b0 %
1"
#100000
0!
b0 $
0"
#105000
b1 %
1"
#110000
b1 $
0"
#115000
b10 %
1"
#120000
b10 $
0"
#125000
b11 %
1"
#130000
b11 $
0"
#135000
1!
b100 %
1"
#140000
b100 $
0"
#145000
b101 %
1"
#150000
b101 $
0"
#155000
b110 %
1"
#160000
b110 $
0"
#165000
b0 %
1"
#170000
0!
b0 $
0"
#175000
b1 %
1"
#180000
b1 $
0"
#185000
b10 %
1"
#190000
b10 $
0"
#195000
b11 %
1"
#200000
b11 $
0"
#205000
1!
b100 %
1"
#210000
b100 $
0"
#215000
b101 %
1"
#220000
b101 $
0"
#225000
b110 %
1"
#230000
b110 $
0"
#235000
b0 %
1"
#240000
0!
b0 $
0"
#245000
b1 %
1"
#250000
b1 $
0"
#255000
b10 %
1"
#260000
b10 $
0"
#265000
b11 %
1"
#270000
b11 $
0"
#275000
1!
b100 %
1"
#280000
b100 $
0"
#285000
b101 %
1"
#290000
b101 $
0"
#295000
b110 %
1"
#300000
b110 $
0"
#305000
b0 %
1"
#310000
0!
b0 $
0"
#315000
b1 %
1"
#320000
b1 $
0"
#325000
b10 %
1"
#330000
b10 $
0"
#335000
b11 %
1"
#340000
b11 $
0"
#345000
1!
b100 %
1"
#350000
b100 $
0"
#355000
b101 %
1"
#360000
b101 $
0"
#365000
b110 %
1"
#370000
b110 $
0"
#375000
b0 %
1"
#380000
0!
b0 $
0"
#385000
b1 %
1"
#390000
b1 $
0"
#395000
b10 %
1"
#400000
b10 $
0"
#405000
b11 %
1"
#410000
b11 $
0"
#415000
1!
b100 %
1"
#420000
b100 $
0"
#425000
b101 %
1"
#430000
b101 $
0"
#435000
b110 %
1"
#440000
b110 $
0"
#445000
b0 %
1"
#450000
0!
b0 $
0"
#455000
b1 %
1"
#460000
b1 $
0"
#465000
b10 %
1"
#470000
b10 $
0"
#475000
b11 %
1"
#480000
b11 $
0"
#485000
1!
b100 %
1"
#490000
b100 $
0"
#495000
b101 %
1"
#500000
b101 $
0"
#505000
b110 %
1"
#510000
b110 $
0"
#515000
b0 %
1"
#520000
0!
b0 $
0"
#525000
b1 %
1"
#530000
b1 $
0"
#535000
b10 %
1"
#540000
b10 $
0"
#545000
b11 %
1"
#550000
b11 $
0"
#555000
1!
b100 %
1"
#560000
b100 $
0"
#565000
b101 %
1"
#570000
b101 $
0"
#575000
b110 %
1"
#580000
b110 $
0"
#585000
b0 %
1"
#590000
0!
b0 $
0"
#595000
b1 %
1"
#600000
b1 $
0"
#605000
b10 %
1"
#610000
b10 $
0"
#615000
b11 %
1"
#620000
b11 $
0"
#625000
1!
b100 %
1"
#630000
b100 $
0"
#635000
b101 %
1"
#640000
b101 $
0"
#645000
b110 %
1"
#650000
b110 $
0"
#655000
b0 %
1"
#660000
0!
b0 $
0"
#665000
b1 %
1"
#670000
b1 $
0"
#675000
b10 %
1"
#680000
b10 $
0"
#685000
b11 %
1"
#690000
b11 $
0"
#695000
1!
b100 %
1"
#700000
b100 $
0"
#705000
b101 %
1"
#710000
b101 $
0"
#715000
b110 %
1"
#720000
b110 $
0"
#725000
b0 %
1"
#730000
0!
b0 $
0"
#735000
b1 %
1"
#740000
b1 $
0"
#745000
b10 %
1"
#750000
b10 $
0"
#755000
b11 %
1"
#760000
b11 $
0"
#765000
1!
b100 %
1"
#770000
b100 $
0"
#775000
b101 %
1"
#780000
b101 $
0"
#785000
b110 %
1"
#790000
b110 $
0"
#795000
b0 %
1"
#800000
0!
b0 $
0"
#805000
b1 %
1"
#810000
b1 $
0"
#815000
b10 %
1"
#820000
b10 $
0"
#825000
b11 %
1"
#830000
b11 $
0"
#835000
1!
b100 %
1"
#840000
b100 $
0"
#845000
b101 %
1"
#850000
b101 $
0"
#855000
b110 %
1"
#860000
b110 $
0"
#865000
b0 %
1"
#870000
0!
b0 $
0"
#875000
b1 %
1"
#880000
b1 $
0"
#885000
b10 %
1"
#890000
b10 $
0"
#895000
b11 %
1"
#900000
b11 $
0"
#905000
1!
b100 %
1"
#910000
b100 $
0"
#915000
b101 %
1"
#920000
b101 $
0"
#925000
b110 %
1"
#930000
b110 $
0"
#935000
b0 %
1"
#940000
0!
b0 $
0"
#945000
b1 %
1"
#950000
b1 $
0"
#955000
b10 %
1"
#960000
b10 $
0"
#965000
b11 %
1"
#970000
b11 $
0"
#975000
1!
b100 %
1"
#980000
b100 $
0"
#985000
b101 %
1"
#990000
b101 $
0"
#995000
b110 %
1"
#1000000
b110 $
0"
#1005000
b0 %
1"
#1010000
0!
b0 $
0"
#1015000
b1 %
1"
#1020000
b1 $
0"
#1025000
b10 %
1"
#1030000
b10 $
0"
