MCDF/control_register/control_register.v
/*************************<MCDF控制寄存器>*********************/
//存储器仅在时钟周期完成读或写，并不完成同时读写
`timescale 1ns/100ps
/*************************<端口声明>*********************/
module control_register
#(
    parameter   CTRL_REG_DEFAULT='b111,
                STATE_REG_DEFAULT='d64 //FIFO深度
              
)
(
    input                   clk_i,
                            rstn_i,
    input   wire    [1:0]   cmd_i ,
    input   wire    [5:0]   cmd_addr_i,
    input   wire    [31:0]  cmd_data_i,    
    input   wire    [5:0]   slv0_margin_i,
                            slv1_margin_i,
                            slv2_margin_i,


    output                  slv0_en_o,
                            slv1_en_o,
                            slv2_en_o,    
    output  reg     [31:0]  cmd_data_o,
    output  wire    [1:0]   slv0_prio_o,
                            slv1_prio_o,
                            slv2_prio_o,
    output  wire    [2:0]   slv0_pkglen_o,
                            slv1_pkglen_o,
                            slv2_pkglen_o
);
/*************************<中间信号>*********************/
reg     [31:0]   Register    [5:0];//6个寄存器构成的存储单元
integer i;
/*************************<时序电路>*********************/
always @(posedge clk_i or negedge rstn_i) begin
    if(!rstn_i)begin//给寄存器赋复位值
        for(i=0;i<3;i=i+1)begin
            Register[i]<=CTRL_REG_DEFAULT;
        end
        for(i=4;i<6;i=i+1)begin
            Register[i]<=STATE_REG_DEFAULT;
        end
        cmd_data_o<='d0;//!!!不加这句不给综合
    end
    else begin
        case (cmd_i)
        //!!!这里没有加入状态寄存器不能写的约束，所有寄存器均可读写，并且读取的通道余量是延迟一个时钟的
            'b01:cmd_data_o<=Register[cmd_addr_i>>4];//RD
            'b10:Register[cmd_addr_i>>4]<=cmd_data_i;//WR
            default: //IDLE
                ;//不做任何操作但是要加上，防止综合出锁存器
        endcase
        //锁存更新通道余量
        Register[0][5:3]<=slv0_margin_i;
        Register[1][5:3]<=slv1_margin_i;
        Register[2][5:3]<=slv2_margin_i;        
    end
end
/*************************<组合逻辑电路>*********************/
//通道使能信号
assign slv0_en_o=Register[0][0];
assign slv1_en_o=Register[1][0];
assign slv2_en_o=Register[2][0];
//通道优先级
assign slv0_prio_o=Register[0][2:1];
assign slv1_prio_o=Register[1][2:1];
assign slv2_prio_o=Register[2][2:1];
//数据包长度
assign slv0_pkglen_o=Register[0][5:3];
assign slv1_pkglen_o=Register[1][5:3];
assign slv2_pkglen_o=Register[2][5:3];
endmodule

MCDF/control_register/control_register_tb.v
`timescale 1ns/100ps
`include "control_register.v"
/*************************<端口声明>*********************/
module control_register_tb;
reg             clk_i,
                rstn_i;
reg     [1:0]   cmd_i;
reg     [5:0]   cmd_addr_i;
reg     [31:0]  cmd_data_i;    
reg     [5:0]   slv0_margin_i,
                slv1_margin_i,
                slv2_margin_i;


wire            slv0_en_o,
                slv1_en_o,
                slv2_en_o;    
wire    [31:0]  cmd_data_o;
wire    [1:0]   slv0_prio_o,
                slv1_prio_o,
                slv2_prio_o;
wire    [2:0]   slv0_pkglen_o,
                slv1_pkglen_o,
                slv2_pkglen_o;
/*************************<原件例化>*********************/
control_register cr1(
                clk_i,
                rstn_i,
                cmd_i,
                cmd_addr_i,
                cmd_data_i,   
                slv0_margin_i,
                slv1_margin_i,
                slv2_margin_i,
                
                slv0_en_o,
                slv1_en_o,
                slv2_en_o,
                cmd_data_o,
                slv0_prio_o,
                slv1_prio_o,
                slv2_prio_o,
                slv0_pkglen_o,
                slv1_pkglen_o,
                slv2_pkglen_o
);
/*************************<激励信号>*********************/
initial begin
    clk_i=0;
    rstn_i=0;
    cmd_i='b00;
    cmd_addr_i='b00;
    cmd_data_i='hC3;  
    slv0_margin_i='d21;
    slv1_margin_i='d33;
    slv2_margin_i='d45;    
    $dumpfile("control_register.vcd");
    $dumpvars;
    #25 rstn_i=1;
    @(posedge clk_i)begin
        cmd_i='b10;
        cmd_addr_i='d00;
        cmd_data_i='hD1;     
    end
    @(posedge clk_i)begin
        cmd_i='b10;
        cmd_addr_i='d04;
        cmd_data_i='hD2;     
    end
    @(posedge clk_i)begin
        cmd_i='b10;
        cmd_addr_i='d08;
        cmd_data_i='hD3;     
    end
    @(posedge clk_i)begin
        cmd_i='b00;
        cmd_addr_i='d08;
        cmd_data_i='hD3;     
    end
    @(posedge clk_i)begin
        cmd_i='b10;
        cmd_addr_i='d00;
        cmd_data_i='hD4;     
    end
    @(posedge clk_i)begin
        cmd_i='b01;
        cmd_addr_i='d04;
        cmd_data_i='hD4;     
    end
    @(posedge clk_i)begin
        cmd_i='b01;
        cmd_addr_i='d00;
        cmd_data_i='hD4;     
    end
    #500 $finish;
end
always #10
    clk_i=~clk_i;

endmodule

MCDF/control_register/control_register.vcd
$date
	Fri Dec  2 23:36:34 2022
$end
$version
	Icarus Verilog
$end
$timescale
	100ps
$end
$scope module control_register_tb $end
$var wire 2 ! slv2_prio_o [1:0] $end
$var wire 3 " slv2_pkglen_o [2:0] $end
$var wire 1 # slv2_en_o $end
$var wire 2 $ slv1_prio_o [1:0] $end
$var wire 3 % slv1_pkglen_o [2:0] $end
$var wire 1 & slv1_en_o $end
$var wire 2 ' slv0_prio_o [1:0] $end
$var wire 3 ( slv0_pkglen_o [2:0] $end
$var wire 1 ) slv0_en_o $end
$var wire 32 * cmd_data_o [31:0] $end
$var reg 1 + clk_i $end
$var reg 6 , cmd_addr_i [5:0] $end
$var reg 32 - cmd_data_i [31:0] $end
$var reg 2 . cmd_i [1:0] $end
$var reg 1 / rstn_i $end
$var reg 6 0 slv0_margin_i [5:0] $end
$var reg 6 1 slv1_margin_i [5:0] $end
$var reg 6 2 slv2_margin_i [5:0] $end
$scope module cr1 $end
$var wire 1 + clk_i $end
$var wire 6 3 cmd_addr_i [5:0] $end
$var wire 32 4 cmd_data_i [31:0] $end
$var wire 2 5 cmd_i [1:0] $end
$var wire 1 / rstn_i $end
$var wire 6 6 slv0_margin_i [5:0] $end
$var wire 6 7 slv1_margin_i [5:0] $end
$var wire 6 8 slv2_margin_i [5:0] $end
$var wire 2 9 slv2_prio_o [1:0] $end
$var wire 3 : slv2_pkglen_o [2:0] $end
$var wire 1 # slv2_en_o $end
$var wire 2 ; slv1_prio_o [1:0] $end
$var wire 3 < slv1_pkglen_o [2:0] $end
$var wire 1 & slv1_en_o $end
$var wire 2 = slv0_prio_o [1:0] $end
$var wire 3 > slv0_pkglen_o [2:0] $end
$var wire 1 ) slv0_en_o $end
$var reg 32 ? cmd_data_o [31:0] $end
$var integer 32 @ i [31:0] $end
$upscope $end
$upscope $end
$enddefinitions $end
#0
$dumpvars
b110 @
b0 ?
b0 >
b11 =
b0 <
b11 ;
b0 :
b11 9
b101101 8
b100001 7
b10101 6
b0 5
b11000011 4
b0 3
b101101 2
b100001 1
b10101 0
0/
b0 .
b11000011 -
b0 ,
0+
b0 *
1)
b0 (
b11 '
1&
b0 %
b11 $
1#
b0 "
b11 !
$end
#100
b110 @
1+
#200
0+
#250
1/
#300
b101 "
b101 :
b1 %
b1 <
b0 '
b0 =
b101 (
b101 >
b11010001 -
b11010001 4
b10 .
b10 5
1+
#400
0+
#500
0)
b1 '
b1 =
b11010010 -
b11010010 4
b100 ,
b100 3
1+
#600
0+
#700
1)
b11010011 -
b11010011 4
b1000 ,
b1000 3
1+
#800
0+
#900
b0 .
b0 5
1+
#1000
0+
#1100
0)
b10 '
b10 =
b11010100 -
b11010100 4
b0 ,
b0 3
b10 .
b10 5
1+
#1200
0+
#1300
b11101100 *
b11101100 ?
b100 ,
b100 3
b1 .
b1 5
1+
#1400
0+
#1500
b0 ,
b0 3
1+
