协议合集/UART/test_code/receiver.v
//uart接收器
//16倍频采样，采取中间3个多数结果
//???接受数据时是否需要打2拍避免亚稳态
module receiver #(
parameter data_width = 8)
(
    input rx_clk,
    input rst_n,
    input data_in,
    output [data_width-1:0]rx_out
);

//状态机定义
localparam IDLE 	= 3'b000;
localparam START 	= 3'b001;//发送低电平
localparam DATA	 	= 3'b010;
localparam CRC 	 	= 3'b011;//校验,但暂时不用
localparam FINISH   = 3'b100;

reg [2:0] state, nstate;

//
reg [3:0] frq_16;       //16倍采样计数器
reg data_in_reg;
reg [15:0] filter_reg;  //16倍频采样数据寄存器
reg filter_out;         //16倍采样结果

reg [data_width-1:0] rx_out_reg;
reg test_reg;



wire start_flag;


reg [3:0] count_data;
reg [1:0] count_stop;

//三段式状态机的第一段
always@(posedge rx_clk or negedge rst_n)
	if(!rst_n)
		state <= IDLE;
	else
		state <= nstate;

//三段式状态机的第二段
always@(*)
	begin
	case(state)
		IDLE:       nstate = (start_flag ? START : IDLE);//根据接收到下降沿进入工作状态
		START:		nstate = (frq_16 == 4'b1111 ? DATA : START);
		DATA:		nstate = (frq_16 == 4'b1111 && count_data == data_width - 1) ? FINISH : DATA ;
		//本例不用的状态
        CRC:		nstate = (frq_16 == 4'b1111 ? FINISH : CRC);
		
        FINISH:		nstate = (frq_16 == 4'b1111 ? IDLE : FINISH);
	default:nstate = IDLE;
	endcase
	end

//下降沿检测电路，输出start信号，激活UART接收，以离开IDLE状态
//************************************************************
always@(posedge rx_clk or negedge rst_n)
	if(!rst_n)
		data_in_reg <= 1'b0;
	else
		data_in_reg <= data_in;

assign start_flag = data_in_reg & !data_in;//下降沿检测器
//**************************************************************



//数据位数8计数器
//**************************************************************
always@(posedge rx_clk or negedge rst_n)
	if(!rst_n || state != DATA)//清零或离开数据状态归零 
		count_data <= 4'b0000;
	else if (frq_16 == 4'b1111)//在数据状态内根据16倍采样器进1
		count_data <= count_data + 1'b1;
	else                        //16倍采样器未满时保持不变
		count_data <= count_data;
//**************************************************************		



//16倍的采样计数器，离开了IDLE才开始计数
//********************************************************************
always@(posedge rx_clk or negedge rst_n)
	if(!rst_n)
		frq_16 <= 4'b0000;
	else if(frq_16 == 4'b1111 || state == IDLE)//IDLE态为0，满15归0
		frq_16 <= 4'b0000;
	else 
		frq_16 <= frq_16 + 1'b1;
//********************************************************************


//16倍频的采样结果存储在filter_reg中
always@(posedge rx_clk or negedge rst_n)
	if(!rst_n)
		filter_reg <= 16'h0000;
	else if(state == START || state == DATA || state == CRC || state == FINISH)//工作状态都16倍频采样
		filter_reg[frq_16] <= data_in;//目前仅使用DATA16倍采样数据
	else
		filter_reg <= 16'h0000;

//存储后的多路选择,结果输出位filter_out
//12拍时取中间时刻的多数表决结果作为当拍最终结果
//********************************************************************
always@(posedge rx_clk or negedge rst_n)
	if(!rst_n || state == IDLE)
		filter_out <= 1'b0;
	else if ( frq_16 == 4'b1100)
		filter_out <= (filter_reg[7] & filter_reg[8]) ^ (filter_reg[7] & filter_reg[9]) ^ (filter_reg[8] & filter_reg[9]);
	else
		filter_out <= filter_out;
//********************************************************************



//DATA状态时将数据依次存入寄存器rx_out_reg
//********************************************************************
always@(posedge rx_clk or negedge rst_n)
			if(!rst_n || state == IDLE)
				rx_out_reg <= 'b0;
			else if (state == DATA && frq_16 == 4'b1111)
				rx_out_reg[count_data] <= filter_out;
			else 
				rx_out_reg <= rx_out_reg;
//********************************************************************


//在finish状态，将rx_out_reg作为rx_out的有效数据
//********************************************************************
assign rx_out =(state == FINISH) ? rx_out_reg : 'b0 ;
//********************************************************************

endmodule

协议合集/UART/test_code/transmitter_gen.v
//用于上板测试，使发送模块重复发送数据。
module transmitter_gen(
    input tx_clk,
    input rst_n,
    output  enable,
    output  [7:0]   data_generated
);
reg [4:0]  gen_counter;//发送的周期可以放大点
assign data_generated=8'h78;
assign enable=(gen_counter==5'b11111)?1:0;
always @(posedge tx_clk,negedge rst_n) begin
    if(~rst_n)
            gen_counter<=0;
    else
            gen_counter<=gen_counter+1; 
end
endmodule

协议合集/UART/test_code/transmitter.v
//uart发射模块
/****
简化为8位传输，1位结束符，无校验位
*****/
//重点学习，带计数器的状态机写法
module transmitter
#(parameter data_width = 8//数据宽度8位
    )
(
input tx_clk,
input rst_n,
input [data_width-1:0] data_in,
input enable,//输入使能位
output reg tx_out);

localparam IDLE 	= 3'b000;
localparam START 	= 3'b001;//发送低电平
localparam DATA	 	= 3'b010;
localparam CRC 	 	= 3'b011;//校验,但暂时不用
localparam FINISH   = 3'b100;

reg [3:0] state, nstate;
reg [3:0] count_data;//输出数据位计数器

//状态机第一段
always@(posedge tx_clk or negedge rst_n)
	if(!rst_n)
		state <= IDLE;
	else
		state <= nstate;

//状态机第二段
always@(*)
	begin
	case(state)
		IDLE: 		nstate = (enable ? START : IDLE);//注意enable的时序
		START:		nstate =  DATA ;
		DATA:		nstate = (count_data == (data_width - 1)? FINISH : DATA); 
		CRC:		nstate =  FINISH ;//正常情况进不来CRC的
		FINISH:		nstate =  IDLE;//注意count_data和count_stop的时序
	default: nstate = IDLE;
	endcase
	end
	
//状态机的输出
always@(*)
	case(state)
		IDLE : tx_out = 1'b1;
		START : tx_out = 1'b0;
		DATA : tx_out = data_in[count_data]; //由低位到高位依次输出
		CRC : tx_out = 1'b0;
		FINISH : tx_out = 1'b1;
	default : tx_out = 1'b1;
	endcase

//DATA状态，输出数据位的计数器
always@(posedge tx_clk or negedge rst_n)
	if(!rst_n)
		count_data <= 4'b0000;
	else if (count_data < data_width && state == DATA)
		count_data <= count_data + 1'b1;
	else 
		count_data <= 4'b0000;


endmodule

协议合集/UART/test_code/rxtx_tb.v
`timescale 1ns/1ps
`include "transmitter.v"
`include "transmitter_gen.v"
`include "receiver.v"
module rxtx_tb;
parameter data_width = 8;

reg tx_clk,rx_clk;
reg rst_n;

wire [data_width-1:0] data_source;
wire [data_width-1:0] rx_out;
wire enable;
wire tx_out;
//***************<模块实例化>******************
transmitter tm1(
    tx_clk,
    rst_n,
    data_source,
    enable,

    tx_out
);

transmitter_gen tg1(
    tx_clk,
    rst_n,
    
    enable,
    data_source
);

receiver rv1(
    rx_clk,
    rst_n,
    tx_out,

    rx_out
);

// initial begin
//     tx_clk<=1'b0;
//     rst_n<=1'b0;
//     data_in<=$random;
//     enable<=0;
//     $dumpfile("transmitter.vcd");
//     $dumpvars;
//     #45 rst_n<=1;
//     repeat(10)begin
//         data_in<=$random;
//        @(posedge tx_clk)    enable<=1;
//        @(posedge tx_clk)    enable<=0; 
//     #400;
//     end

//     #1000 $finish;
// end
initial begin
    tx_clk<=1'b0;
    rx_clk<=1'b0;
    rst_n<=1'b0;
    $dumpfile("rttx.vcd");
    $dumpvars;
    #45 rst_n<=1;
    #10000 $finish;
end

always #60
    tx_clk<=~tx_clk;
always #5
    rx_clk<=~rx_clk;
endmodule

协议合集/UART/test_code/rttx.vcd
$date
	Sat Mar 11 11:19:16 2023
$end
$version
	Icarus Verilog
$end
$timescale
	1ps
$end
$scope module rxtx_tb $end
$var wire 8 ! data_source [7:0] $end
$var wire 1 " tx_out $end
$var wire 8 # rx_out [7:0] $end
$var wire 1 $ enable $end
$var parameter 32 % data_width $end
$var reg 1 & rst_n $end
$var reg 1 ' rx_clk $end
$var reg 1 ( tx_clk $end
$scope module rv1 $end
$var wire 1 & rst_n $end
$var wire 1 ' rx_clk $end
$var wire 1 ) start_flag $end
$var wire 8 * rx_out [7:0] $end
$var wire 1 " data_in $end
$var parameter 3 + CRC $end
$var parameter 3 , DATA $end
$var parameter 3 - FINISH $end
$var parameter 3 . IDLE $end
$var parameter 3 / START $end
$var parameter 32 0 data_width $end
$var reg 4 1 count_data [3:0] $end
$var reg 1 2 data_in_reg $end
$var reg 1 3 filter_out $end
$var reg 16 4 filter_reg [15:0] $end
$var reg 4 5 frq_16 [3:0] $end
$var reg 3 6 nstate [2:0] $end
$var reg 8 7 rx_out_reg [7:0] $end
$var reg 3 8 state [2:0] $end
$upscope $end
$scope module tg1 $end
$var wire 8 9 data_generated [7:0] $end
$var wire 1 & rst_n $end
$var wire 1 ( tx_clk $end
$var wire 1 $ enable $end
$var reg 5 : gen_counter [4:0] $end
$upscope $end
$scope module tm1 $end
$var wire 8 ; data_in [7:0] $end
$var wire 1 $ enable $end
$var wire 1 & rst_n $end
$var wire 1 ( tx_clk $end
$var parameter 3 < CRC $end
$var parameter 3 = DATA $end
$var parameter 3 > FINISH $end
$var parameter 3 ? IDLE $end
$var parameter 3 @ START $end
$var parameter 32 A data_width $end
$var reg 4 B count_data [3:0] $end
$var reg 4 C nstate [3:0] $end
$var reg 4 D state [3:0] $end
$var reg 1 " tx_out $end
$upscope $end
$upscope $end
$enddefinitions $end
$comment Show the parameter values. $end
$dumpall
b1000 A
b1 @
b0 ?
b100 >
b10 =
b11 <
b1000 0
b1 /
b0 .
b100 -
b10 ,
b11 +
b1000 %
$end
#0
$dumpvars
b0 D
b0 C
b0 B
b1111000 ;
b0 :
b1111000 9
b0 8
b0 7
b0 6
b0 5
b0 4
03
02
b0 1
b0 *
0)
0(
0'
0&
0$
b0 #
1"
b1111000 !
$end
#5000
1'
#10000
0'
#15000
1'
#20000
0'
#25000
1'
#30000
0'
#35000
1'
#40000
0'
#45000
12
1'
1&
#50000
0'
#55000
1'
#60000
b1 :
0'
1(
#65000
1'
#70000
0'
#75000
1'
#80000
0'
#85000
1'
#90000
0'
#95000
1'
#100000
0'
#105000
1'
#110000
0'
#115000
1'
#120000
0'
0(
#125000
1'
#130000
0'
#135000
1'
#140000
0'
#145000
1'
#150000
0'
#155000
1'
#160000
0'
#165000
1'
#170000
0'
#175000
1'
#180000
b10 :
0'
1(
#185000
1'
#190000
0'
#195000
1'
#200000
0'
#205000
1'
#210000
0'
#215000
1'
#220000
0'
#225000
1'
#230000
0'
#235000
1'
#240000
0'
0(
#245000
1'
#250000
0'
#255000
1'
#260000
0'
#265000
1'
#270000
0'
#275000
1'
#280000
0'
#285000
1'
#290000
0'
#295000
1'
#300000
b11 :
0'
1(
#305000
1'
#310000
0'
#315000
1'
#320000
0'
#325000
1'
#330000
0'
#335000
1'
#340000
0'
#345000
1'
#350000
0'
#355000
1'
#360000
0'
0(
#365000
1'
#370000
0'
#375000
1'
#380000
0'
#385000
1'
#390000
0'
#395000
1'
#400000
0'
#405000
1'
#410000
0'
#415000
1'
#420000
b100 :
0'
1(
#425000
1'
#430000
0'
#435000
1'
#440000
0'
#445000
1'
#450000
0'
#455000
1'
#460000
0'
#465000
1'
#470000
0'
#475000
1'
#480000
0'
0(
#485000
1'
#490000
0'
#495000
1'
#500000
0'
#505000
1'
#510000
0'
#515000
1'
#520000
0'
#525000
1'
#530000
0'
#535000
1'
#540000
b101 :
0'
1(
#545000
1'
#550000
0'
#555000
1'
#560000
0'
#565000
1'
#570000
0'
#575000
1'
#580000
0'
#585000
1'
#590000
0'
#595000
1'
#600000
0'
0(
#605000
1'
#610000
0'
#615000
1'
#620000
0'
#625000
1'
#630000
0'
#635000
1'
#640000
0'
#645000
1'
#650000
0'
#655000
1'
#660000
b110 :
0'
1(
#665000
1'
#670000
0'
#675000
1'
#680000
0'
#685000
1'
#690000
0'
#695000
1'
#700000
0'
#705000
1'
#710000
0'
#715000
1'
#720000
0'
0(
#725000
1'
#730000
0'
#735000
1'
#740000
0'
#745000
1'
#750000
0'
#755000
1'
#760000
0'
#765000
1'
#770000
0'
#775000
1'
#780000
b111 :
0'
1(
#785000
1'
#790000
0'
#795000
1'
#800000
0'
#805000
1'
#810000
0'
#815000
1'
#820000
0'
#825000
1'
#830000
0'
#835000
1'
#840000
0'
0(
#845000
1'
#850000
0'
#855000
1'
#860000
0'
#865000
1'
#870000
0'
#875000
1'
#880000
0'
#885000
1'
#890000
0'
#895000
1'
#900000
b1000 :
0'
1(
#905000
1'
#910000
0'
#915000
1'
#920000
0'
#925000
1'
#930000
0'
#935000
1'
#940000
0'
#945000
1'
#950000
0'
#955000
1'
#960000
0'
0(
#965000
1'
#970000
0'
#975000
1'
#980000
0'
#985000
1'
#990000
0'
#995000
1'
#1000000
0'
#1005000
1'
#1010000
0'
#1015000
1'
#1020000
b1001 :
0'
1(
#1025000
1'
#1030000
0'
#1035000
1'
#1040000
0'
#1045000
1'
#1050000
0'
#1055000
1'
#1060000
0'
#1065000
1'
#1070000
0'
#1075000
1'
#1080000
0'
0(
#1085000
1'
#1090000
0'
#1095000
1'
#1100000
0'
#1105000
1'
#1110000
0'
#1115000
1'
#1120000
0'
#1125000
1'
#1130000
0'
#1135000
1'
#1140000
b1010 :
0'
1(
#1145000
1'
#1150000
0'
#1155000
1'
#1160000
0'
#1165000
1'
#1170000
0'
#1175000
1'
#1180000
0'
#1185000
1'
#1190000
0'
#1195000
1'
#1200000
0'
0(
#1205000
1'
#1210000
0'
#1215000
1'
#1220000
0'
#1225000
1'
#1230000
0'
#1235000
1'
#1240000
0'
#1245000
1'
#1250000
0'
#1255000
1'
#1260000
b1011 :
0'
1(
#1265000
1'
#1270000
0'
#1275000
1'
#1280000
0'
#1285000
1'
#1290000
0'
#1295000
1'
#1300000
0'
#1305000
1'
#1310000
0'
#1315000
1'
#1320000
0'
0(
#1325000
1'
#1330000
0'
#1335000
1'
#1340000
0'
#1345000
1'
#1350000
0'
#1355000
1'
#1360000
0'
#1365000
1'
#1370000
0'
#1375000
1'
#1380000
b1100 :
0'
1(
#1385000
1'
#1390000
0'
#1395000
1'
#1400000
0'
#1405000
1'
#1410000
0'
#1415000
1'
#1420000
0'
#1425000
1'
#1430000
0'
#1435000
1'
#1440000
0'
0(
#1445000
1'
#1450000
0'
#1455000
1'
#1460000
0'
#1465000
1'
#1470000
0'
#1475000
1'
#1480000
0'
#1485000
1'
#1490000
0'
#1495000
1'
#1500000
b1101 :
0'
1(
#1505000
1'
#1510000
0'
#1515000
1'
#1520000
0'
#1525000
1'
#1530000
0'
#1535000
1'
#1540000
0'
#1545000
1'
#1550000
0'
#1555000
1'
#1560000
0'
0(
#1565000
1'
#1570000
0'
#1575000
1'
#1580000
0'
#1585000
1'
#1590000
0'
#1595000
1'
#1600000
0'
#1605000
1'
#1610000
0'
#1615000
1'
#1620000
b1110 :
0'
1(
#1625000
1'
#1630000
0'
#1635000
1'
#1640000
0'
#1645000
1'
#1650000
0'
#1655000
1'
#1660000
0'
#1665000
1'
#1670000
0'
#1675000
1'
#1680000
0'
0(
#1685000
1'
#1690000
0'
#1695000
1'
#1700000
0'
#1705000
1'
#1710000
0'
#1715000
1'
#1720000
0'
#1725000
1'
#1730000
0'
#1735000
1'
#1740000
b1111 :
0'
1(
#1745000
1'
#1750000
0'
#1755000
1'
#1760000
0'
#1765000
1'
#1770000
0'
#1775000
1'
#1780000
0'
#1785000
1'
#1790000
0'
#1795000
1'
#1800000
0'
0(
#1805000
1'
#1810000
0'
#1815000
1'
#1820000
0'
#1825000
1'
#1830000
0'
#1835000
1'
#1840000
0'
#1845000
1'
#1850000
0'
#1855000
1'
#1860000
b10000 :
0'
1(
#1865000
1'
#1870000
0'
#1875000
1'
#1880000
0'
#1885000
1'
#1890000
0'
#1895000
1'
#1900000
0'
#1905000
1'
#1910000
0'
#1915000
1'
#1920000
0'
0(
#1925000
1'
#1930000
0'
#1935000
1'
#1940000
0'
#1945000
1'
#1950000
0'
#1955000
1'
#1960000
0'
#1965000
1'
#1970000
0'
#1975000
1'
#1980000
b10001 :
0'
1(
#1985000
1'
#1990000
0'
#1995000
1'
#2000000
0'
#2005000
1'
#2010000
0'
#2015000
1'
#2020000
0'
#2025000
1'
#2030000
0'
#2035000
1'
#2040000
0'
0(
#2045000
1'
#2050000
0'
#2055000
1'
#2060000
0'
#2065000
1'
#2070000
0'
#2075000
1'
#2080000
0'
#2085000
1'
#2090000
0'
#2095000
1'
#2100000
b10010 :
0'
1(
#2105000
1'
#2110000
0'
#2115000
1'
#2120000
0'
#2125000
1'
#2130000
0'
#2135000
1'
#2140000
0'
#2145000
1'
#2150000
0'
#2155000
1'
#2160000
0'
0(
#2165000
1'
#2170000
0'
#2175000
1'
#2180000
0'
#2185000
1'
#2190000
0'
#2195000
1'
#2200000
0'
#2205000
1'
#2210000
0'
#2215000
1'
#2220000
b10011 :
0'
1(
#2225000
1'
#2230000
0'
#2235000
1'
#2240000
0'
#2245000
1'
#2250000
0'
#2255000
1'
#2260000
0'
#2265000
1'
#2270000
0'
#2275000
1'
#2280000
0'
0(
#2285000
1'
#2290000
0'
#2295000
1'
#2300000
0'
#2305000
1'
#2310000
0'
#2315000
1'
#2320000
0'
#2325000
1'
#2330000
0'
#2335000
1'
#2340000
b10100 :
0'
1(
#2345000
1'
#2350000
0'
#2355000
1'
#2360000
0'
#2365000
1'
#2370000
0'
#2375000
1'
#2380000
0'
#2385000
1'
#2390000
0'
#2395000
1'
#2400000
0'
0(
#2405000
1'
#2410000
0'
#2415000
1'
#2420000
0'
#2425000
1'
#2430000
0'
#2435000
1'
#2440000
0'
#2445000
1'
#2450000
0'
#2455000
1'
#2460000
b10101 :
0'
1(
#2465000
1'
#2470000
0'
#2475000
1'
#2480000
0'
#2485000
1'
#2490000
0'
#2495000
1'
#2500000
0'
#2505000
1'
#2510000
0'
#2515000
1'
#2520000
0'
0(
#2525000
1'
#2530000
0'
#2535000
1'
#2540000
0'
#2545000
1'
#2550000
0'
#2555000
1'
#2560000
0'
#2565000
1'
#2570000
0'
#2575000
1'
#2580000
b10110 :
0'
1(
#2585000
1'
#2590000
0'
#2595000
1'
#2600000
0'
#2605000
1'
#2610000
0'
#2615000
1'
#2620000
0'
#2625000
1'
#2630000
0'
#2635000
1'
#2640000
0'
0(
#2645000
1'
#2650000
0'
#2655000
1'
#2660000
0'
#2665000
1'
#2670000
0'
#2675000
1'
#2680000
0'
#2685000
1'
#2690000
0'
#2695000
1'
#2700000
b10111 :
0'
1(
#2705000
1'
#2710000
0'
#2715000
1'
#2720000
0'
#2725000
1'
#2730000
0'
#2735000
1'
#2740000
0'
#2745000
1'
#2750000
0'
#2755000
1'
#2760000
0'
0(
#2765000
1'
#2770000
0'
#2775000
1'
#2780000
0'
#2785000
1'
#2790000
0'
#2795000
1'
#2800000
0'
#2805000
1'
#2810000
0'
#2815000
1'
#2820000
b11000 :
0'
1(
#2825000
1'
#2830000
0'
#2835000
1'
#2840000
0'
#2845000
1'
#2850000
0'
#2855000
1'
#2860000
0'
#2865000
1'
#2870000
0'
#2875000
1'
#2880000
0'
0(
#2885000
1'
#2890000
0'
#2895000
1'
#2900000
0'
#2905000
1'
#2910000
0'
#2915000
1'
#2920000
0'
#2925000
1'
#2930000
0'
#2935000
1'
#2940000
b11001 :
0'
1(
#2945000
1'
#2950000
0'
#2955000
1'
#2960000
0'
#2965000
1'
#2970000
0'
#2975000
1'
#2980000
0'
#2985000
1'
#2990000
0'
#2995000
1'
#3000000
0'
0(
#3005000
1'
#3010000
0'
#3015000
1'
#3020000
0'
#3025000
1'
#3030000
0'
#3035000
1'
#3040000
0'
#3045000
1'
#3050000
0'
#3055000
1'
#3060000
b11010 :
0'
1(
#3065000
1'
#3070000
0'
#3075000
1'
#3080000
0'
#3085000
1'
#3090000
0'
#3095000
1'
#3100000
0'
#3105000
1'
#3110000
0'
#3115000
1'
#3120000
0'
0(
#3125000
1'
#3130000
0'
#3135000
1'
#3140000
0'
#3145000
1'
#3150000
0'
#3155000
1'
#3160000
0'
#3165000
1'
#3170000
0'
#3175000
1'
#3180000
b11011 :
0'
1(
#3185000
1'
#3190000
0'
#3195000
1'
#3200000
0'
#3205000
1'
#3210000
0'
#3215000
1'
#3220000
0'
#3225000
1'
#3230000
0'
#3235000
1'
#3240000
0'
0(
#3245000
1'
#3250000
0'
#3255000
1'
#3260000
0'
#3265000
1'
#3270000
0'
#3275000
1'
#3280000
0'
#3285000
1'
#3290000
0'
#3295000
1'
#3300000
b11100 :
0'
1(
#3305000
1'
#3310000
0'
#3315000
1'
#3320000
0'
#3325000
1'
#3330000
0'
#3335000
1'
#3340000
0'
#3345000
1'
#3350000
0'
#3355000
1'
#3360000
0'
0(
#3365000
1'
#3370000
0'
#3375000
1'
#3380000
0'
#3385000
1'
#3390000
0'
#3395000
1'
#3400000
0'
#3405000
1'
#3410000
0'
#3415000
1'
#3420000
b11101 :
0'
1(
#3425000
1'
#3430000
0'
#3435000
1'
#3440000
0'
#3445000
1'
#3450000
0'
#3455000
1'
#3460000
0'
#3465000
1'
#3470000
0'
#3475000
1'
#3480000
0'
0(
#3485000
1'
#3490000
0'
#3495000
1'
#3500000
0'
#3505000
1'
#3510000
0'
#3515000
1'
#3520000
0'
#3525000
1'
#3530000
0'
#3535000
1'
#3540000
b11110 :
0'
1(
#3545000
1'
#3550000
0'
#3555000
1'
#3560000
0'
#3565000
1'
#3570000
0'
#3575000
1'
#3580000
0'
#3585000
1'
#3590000
0'
#3595000
1'
#3600000
0'
0(
#3605000
1'
#3610000
0'
#3615000
1'
#3620000
0'
#3625000
1'
#3630000
0'
#3635000
1'
#3640000
0'
#3645000
1'
#3650000
0'
#3655000
1'
#3660000
b1 C
1$
b11111 :
0'
1(
#3665000
1'
#3670000
0'
#3675000
1'
#3680000
0'
#3685000
1'
#3690000
0'
#3695000
1'
#3700000
0'
#3705000
1'
#3710000
0'
#3715000
1'
#3720000
0'
0(
#3725000
1'
#3730000
0'
#3735000
1'
#3740000
0'
#3745000
1'
#3750000
0'
#3755000
1'
#3760000
0'
#3765000
1'
#3770000
0'
#3775000
1'
#3780000
b1 6
1)
0$
0"
b10 C
b1 D
b0 :
0'
1(
#3785000
0)
02
b1 8
1'
#3790000
0'
#3795000
b1 5
1'
#3800000
0'
#3805000
b10 5
1'
#3810000
0'
#3815000
b11 5
1'
#3820000
0'
#3825000
b100 5
1'
#3830000
0'
#3835000
b101 5
1'
#3840000
0'
0(
#3845000
b110 5
1'
#3850000
0'
#3855000
b111 5
1'
#3860000
0'
#3865000
b1000 5
1'
#3870000
0'
#3875000
b1001 5
1'
#3880000
0'
#3885000
b1010 5
1'
#3890000
0'
#3895000
b1011 5
1'
#3900000
b1 :
b10 D
0'
1(
#3905000
b1100 5
1'
#3910000
0'
#3915000
b1101 5
1'
#3920000
0'
#3925000
b1110 5
1'
#3930000
0'
#3935000
b10 6
b1111 5
1'
#3940000
0'
#3945000
b0 5
b10 8
1'
#3950000
0'
#3955000
b1 5
1'
#3960000
0'
0(
#3965000
b10 5
1'
#3970000
0'
#3975000
b11 5
1'
#3980000
0'
#3985000
b100 5
1'
#3990000
0'
#3995000
b101 5
1'
#4000000
0'
#4005000
b110 5
1'
#4010000
0'
#4015000
b111 5
1'
#4020000
b1 B
b10 :
0'
1(
#4025000
b1000 5
1'
#4030000
0'
#4035000
b1001 5
1'
#4040000
0'
#4045000
b1010 5
1'
#4050000
0'
#4055000
b1011 5
1'
#4060000
0'
#4065000
b1100 5
1'
#4070000
0'
#4075000
b1101 5
1'
#4080000
0'
0(
#4085000
b1110 5
1'
#4090000
0'
#4095000
b1111 5
1'
#4100000
0'
#4105000
b0 5
b1 1
1'
#4110000
0'
#4115000
b1 5
1'
#4120000
0'
#4125000
b10 5
1'
#4130000
0'
#4135000
b11 5
1'
#4140000
b11 :
b10 B
0'
1(
#4145000
b100 5
1'
#4150000
0'
#4155000
b101 5
1'
#4160000
0'
#4165000
b110 5
1'
#4170000
0'
#4175000
b111 5
1'
#4180000
0'
#4185000
b1000 5
1'
#4190000
0'
#4195000
b1001 5
1'
#4200000
0'
0(
#4205000
b1010 5
1'
#4210000
0'
#4215000
b1011 5
1'
#4220000
0'
#4225000
b1100 5
1'
#4230000
0'
#4235000
b1101 5
1'
#4240000
0'
#4245000
b1110 5
1'
#4250000
0'
#4255000
b1111 5
1'
#4260000
1"
b11 B
b100 :
0'
1(
#4265000
b1000000000000000 4
b0 5
b10 1
12
1'
#4270000
0'
#4275000
b1 5
b1000000000000001 4
1'
#4280000
0'
#4285000
b1000000000000011 4
b10 5
1'
#4290000
0'
#4295000
b11 5
b1000000000000111 4
1'
#4300000
0'
#4305000
b1000000000001111 4
b100 5
1'
#4310000
0'
#4315000
b101 5
b1000000000011111 4
1'
#4320000
0'
0(
#4325000
b1000000000111111 4
b110 5
1'
#4330000
0'
#4335000
b111 5
b1000000001111111 4
1'
#4340000
0'
#4345000
b1000000011111111 4
b1000 5
1'
#4350000
0'
#4355000
b1001 5
b1000000111111111 4
1'
#4360000
0'
#4365000
b1000001111111111 4
b1010 5
1'
#4370000
0'
#4375000
b1011 5
b1000011111111111 4
1'
#4380000
b101 :
b100 B
0'
1(
#4385000
b1000111111111111 4
b1100 5
1'
#4390000
0'
#4395000
b1101 5
b1001111111111111 4
13
1'
#4400000
0'
#4405000
b1011111111111111 4
b1110 5
1'
#4410000
0'
#4415000
b1111 5
b1111111111111111 4
1'
#4420000
0'
#4425000
b100 7
b0 5
b11 1
1'
#4430000
0'
#4435000
b1 5
1'
#4440000
0'
0(
#4445000
b10 5
1'
#4450000
0'
#4455000
b11 5
1'
#4460000
0'
#4465000
b100 5
1'
#4470000
0'
#4475000
b101 5
1'
#4480000
0'
#4485000
b110 5
1'
#4490000
0'
#4495000
b111 5
1'
#4500000
b101 B
b110 :
0'
1(
#4505000
b1000 5
1'
#4510000
0'
#4515000
b1001 5
1'
#4520000
0'
#4525000
b1010 5
1'
#4530000
0'
#4535000
b1011 5
1'
#4540000
0'
#4545000
b1100 5
1'
#4550000
0'
#4555000
b1101 5
1'
#4560000
0'
0(
#4565000
b1110 5
1'
#4570000
0'
#4575000
b1111 5
1'
#4580000
0'
#4585000
b1100 7
b0 5
b100 1
1'
#4590000
0'
#4595000
b1 5
1'
#4600000
0'
#4605000
b10 5
1'
#4610000
0'
#4615000
b11 5
1'
#4620000
b111 :
b110 B
0'
1(
#4625000
b100 5
1'
#4630000
0'
#4635000
b101 5
1'
#4640000
0'
#4645000
b110 5
1'
#4650000
0'
#4655000
b111 5
1'
#4660000
0'
#4665000
b1000 5
1'
#4670000
0'
#4675000
b1001 5
1'
#4680000
0'
0(
#4685000
b1010 5
1'
#4690000
0'
#4695000
b1011 5
1'
#4700000
0'
#4705000
b1100 5
1'
#4710000
0'
#4715000
b1101 5
1'
#4720000
0'
#4725000
b1110 5
1'
#4730000
0'
#4735000
b1111 5
1'
#4740000
1)
0"
b100 C
b111 B
b1000 :
0'
1(
#4745000
0)
b11100 7
b111111111111111 4
b0 5
b101 1
02
1'
#4750000
0'
#4755000
b1 5
b111111111111110 4
1'
#4760000
0'
#4765000
b111111111111100 4
b10 5
1'
#4770000
0'
#4775000
b11 5
b111111111111000 4
1'
#4780000
0'
#4785000
b111111111110000 4
b100 5
1'
#4790000
0'
#4795000
b101 5
b111111111100000 4
1'
#4800000
0'
0(
#4805000
b111111111000000 4
b110 5
1'
#4810000
0'
#4815000
b111 5
b111111110000000 4
1'
#4820000
0'
#4825000
b111111100000000 4
b1000 5
1'
#4830000
0'
#4835000
b1001 5
b111111000000000 4
1'
#4840000
0'
#4845000
b111110000000000 4
b1010 5
1'
#4850000
0'
#4855000
b1011 5
b111100000000000 4
1'
#4860000
1"
b0 C
b1001 :
b1000 B
b100 D
0'
1(
#4865000
b1100 5
12
1'
#4870000
0'
#4875000
b1101 5
03
1'
#4880000
0'
#4885000
b1110 5
1'
#4890000
0'
#4895000
b1111 5
1'
#4900000
0'
#4905000
b1111100000000000 4
b0 5
b110 1
1'
#4910000
0'
#4915000
b1 5
b1111100000000001 4
1'
#4920000
0'
0(
#4925000
b1111100000000011 4
b10 5
1'
#4930000
0'
#4935000
b11 5
b1111100000000111 4
1'
#4940000
0'
#4945000
b1111100000001111 4
b100 5
1'
#4950000
0'
#4955000
b101 5
b1111100000011111 4
1'
#4960000
0'
#4965000
b1111100000111111 4
b110 5
1'
#4970000
0'
#4975000
b111 5
b1111100001111111 4
1'
#4980000
b0 D
b0 B
b1010 :
0'
1(
#4985000
b1111100011111111 4
b1000 5
1'
#4990000
0'
#4995000
b1001 5
b1111100111111111 4
1'
#5000000
0'
#5005000
b1111101111111111 4
b1010 5
1'
#5010000
0'
#5015000
b1011 5
b1111111111111111 4
1'
#5020000
0'
#5025000
b1100 5
1'
#5030000
0'
#5035000
b1101 5
13
1'
#5040000
0'
0(
#5045000
b1110 5
1'
#5050000
0'
#5055000
b1111 5
1'
#5060000
0'
#5065000
b1011100 7
b0 5
b111 1
1'
#5070000
0'
#5075000
b1 5
1'
#5080000
0'
#5085000
b10 5
1'
#5090000
0'
#5095000
b11 5
1'
#5100000
b1011 :
0'
1(
#5105000
b100 5
1'
#5110000
0'
#5115000
b101 5
1'
#5120000
0'
#5125000
b110 5
1'
#5130000
0'
#5135000
b111 5
1'
#5140000
0'
#5145000
b1000 5
1'
#5150000
0'
#5155000
b1001 5
1'
#5160000
0'
0(
#5165000
b1010 5
1'
#5170000
0'
#5175000
b1011 5
1'
#5180000
0'
#5185000
b1100 5
1'
#5190000
0'
#5195000
b1101 5
1'
#5200000
0'
#5205000
b1110 5
1'
#5210000
0'
#5215000
b100 6
b1111 5
1'
#5220000
b1100 :
0'
1(
#5225000
b11011100 #
b11011100 *
b11011100 7
b0 5
b1000 1
b100 8
1'
#5230000
0'
#5235000
b0 1
b1 5
1'
#5240000
0'
#5245000
b10 5
1'
#5250000
0'
#5255000
b11 5
1'
#5260000
0'
#5265000
b100 5
1'
#5270000
0'
#5275000
b101 5
1'
#5280000
0'
0(
#5285000
b110 5
1'
#5290000
0'
#5295000
b111 5
1'
#5300000
0'
#5305000
b1000 5
1'
#5310000
0'
#5315000
b1001 5
1'
#5320000
0'
#5325000
b1010 5
1'
#5330000
0'
#5335000
b1011 5
1'
#5340000
b1101 :
0'
1(
#5345000
b1100 5
1'
