协议合集/UART/test_code/transmitter_gen.v
//用于上板测试，使发送模块重复发送数据。
module transmitter_gen(
    input tx_clk,
    input rst_n,
    output  enable,
    output  [7:0]   data_generated
);
reg [4:0]  gen_counter;//发送的周期可以放大点
assign data_generated=8'h78;
assign enable=(gen_counter==5'b11111)?1:0;
always @(posedge tx_clk,negedge rst_n) begin
    if(~rst_n)
            gen_counter<=0;
    else
            gen_counter<=gen_counter+1; 
end
endmodule

协议合集/UART/test_code/transmitter.v
//uart发射模块
//重点学习，带计数器的状态机写法
module transmitter
#(parameter data_width = 8//数据宽度8位
    )
(
input tx_clk,
input rst_n,
input [data_width-1:0] data_in,
input enable,
output reg tx_out);

localparam IDLE = 3'b000;
localparam S1 	 = 3'b001;//发送低电平
localparam S2	 = 3'b010;
localparam S3 	 = 3'b011;//校验,但暂时不用
localparam S4   = 3'b100;

reg [3:0] state, nstate;
reg [3:0] count_data;//输出数据位计数器

//状态机第一段
always@(posedge tx_clk or negedge rst_n)
	if(!rst_n)
		state <= IDLE;
	else
		state <= nstate;

//状态机第二段
always@(*)
	begin
	case(state)
	IDLE: nstate = (enable ? S1 : IDLE);//注意enable的时序
	S1:		nstate =  S2 ;
	S2:		nstate = (count_data == (data_width - 1)? S4 : S2); 
	S3:		nstate =  S4 ;//正常情况进不来S3的
	S4:		nstate =  IDLE;//注意count_data和count_stop的时序
	default: nstate = IDLE;
	endcase
	end
	
//状态机的输出
always@(*)
	case(state)
		IDLE : tx_out = 1'b1;
		S1 : tx_out = 1'b0;
		S2 : tx_out = data_in[count_data]; //由低位到高位依次输出
		S3 : tx_out = 1'b0;
		S4 : tx_out = 1'b1;
	default : tx_out = 1'b1;
	endcase

//S2状态，输出数据位的计数器
always@(posedge tx_clk or negedge rst_n)
	if(!rst_n)
		count_data <= 4'b0000;
	else if (count_data < data_width && state == S2)
		count_data <= count_data + 1'b1;
	else 
		count_data <= 4'b0000;


endmodule

协议合集/UART/test_code/transmitter_tb.v
`timescale 1ns/1ps
`include "transmitter.v"
`include "transmitter_gen.v"
module transmitter_tb;
parameter data_width = 8;
reg tx_clk;
reg rst_n;
wire [data_width-1:0] data_in;
wire enable;
wire tx_out;

transmitter tm1(
    tx_clk,
    rst_n,
    data_in,
    enable,

    tx_out
);

transmitter_gen tg1(
    tx_clk,
    rst_n,
    
    enable,
    data_in
);

// initial begin
//     tx_clk<=1'b0;
//     rst_n<=1'b0;
//     data_in<=$random;
//     enable<=0;
//     $dumpfile("transmitter.vcd");
//     $dumpvars;
//     #45 rst_n<=1;
//     repeat(10)begin
//         data_in<=$random;
//        @(posedge tx_clk)    enable<=1;
//        @(posedge tx_clk)    enable<=0; 
//     #400;
//     end

//     #1000 $finish;
// end
initial begin
    tx_clk<=1'b0;
    rst_n<=1'b0;
    $dumpfile("transmitter.vcd");
    $dumpvars;
    #45 rst_n<=1;
    #4000 $finish;
end

always #10
    tx_clk<=~tx_clk;
endmodule

协议合集/UART/test_code/transmitter.vcd
$date
	Fri Mar 10 23:12:56 2023
$end
$version
	Icarus Verilog
$end
$timescale
	1ps
$end
$scope module transmitter_tb $end
$var wire 8 ! data_in [7:0] $end
$var wire 1 " tx_out $end
$var wire 1 # enable $end
$var reg 1 $ rst_n $end
$var reg 1 % tx_clk $end
$scope module tg1 $end
$var wire 8 & data_generated [7:0] $end
$var wire 1 $ rst_n $end
$var wire 1 % tx_clk $end
$var wire 1 # enable $end
$var reg 5 ' gen_counter [4:0] $end
$upscope $end
$scope module tm1 $end
$var wire 8 ( data_in [7:0] $end
$var wire 1 # enable $end
$var wire 1 $ rst_n $end
$var wire 1 % tx_clk $end
$var reg 4 ) count_data [3:0] $end
$var reg 4 * nstate [3:0] $end
$var reg 4 + state [3:0] $end
$var reg 1 " tx_out $end
$upscope $end
$upscope $end
$enddefinitions $end
#0
$dumpvars
b0 +
b0 *
b0 )
b1111000 (
b0 '
b1111000 &
0%
0$
0#
1"
b1111000 !
$end
#10000
1%
#20000
0%
#30000
1%
#40000
0%
#45000
1$
#50000
b1 '
1%
#60000
0%
#70000
b10 '
1%
#80000
0%
#90000
b11 '
1%
#100000
0%
#110000
b100 '
1%
#120000
0%
#130000
b101 '
1%
#140000
0%
#150000
b110 '
1%
#160000
0%
#170000
b111 '
1%
#180000
0%
#190000
b1000 '
1%
#200000
0%
#210000
b1001 '
1%
#220000
0%
#230000
b1010 '
1%
#240000
0%
#250000
b1011 '
1%
#260000
0%
#270000
b1100 '
1%
#280000
0%
#290000
b1101 '
1%
#300000
0%
#310000
b1110 '
1%
#320000
0%
#330000
b1111 '
1%
#340000
0%
#350000
b10000 '
1%
#360000
0%
#370000
b10001 '
1%
#380000
0%
#390000
b10010 '
1%
#400000
0%
#410000
b10011 '
1%
#420000
0%
#430000
b10100 '
1%
#440000
0%
#450000
b10101 '
1%
#460000
0%
#470000
b10110 '
1%
#480000
0%
#490000
b10111 '
1%
#500000
0%
#510000
b11000 '
1%
#520000
0%
#530000
b11001 '
1%
#540000
0%
#550000
b11010 '
1%
#560000
0%
#570000
b11011 '
1%
#580000
0%
#590000
b11100 '
1%
#600000
0%
#610000
b11101 '
1%
#620000
0%
#630000
b11110 '
1%
#640000
0%
#650000
b1 *
1#
b11111 '
1%
#660000
0%
#670000
0#
0"
b10 *
b1 +
b0 '
1%
#680000
0%
#690000
b1 '
b10 +
1%
#700000
0%
#710000
b1 )
b10 '
1%
#720000
0%
#730000
b11 '
b10 )
1%
#740000
0%
#750000
1"
b11 )
b100 '
1%
#760000
0%
#770000
b101 '
b100 )
1%
#780000
0%
#790000
b101 )
b110 '
1%
#800000
0%
#810000
b111 '
b110 )
1%
#820000
0%
#830000
0"
b100 *
b111 )
b1000 '
1%
#840000
0%
#850000
1"
b0 *
b1001 '
b1000 )
b100 +
1%
#860000
0%
#870000
b0 +
b0 )
b1010 '
1%
#880000
0%
#890000
b1011 '
1%
#900000
0%
#910000
b1100 '
1%
#920000
0%
#930000
b1101 '
1%
#940000
0%
#950000
b1110 '
1%
#960000
0%
#970000
b1111 '
1%
#980000
0%
#990000
b10000 '
1%
#1000000
0%
#1010000
b10001 '
1%
#1020000
0%
#1030000
b10010 '
1%
#1040000
0%
#1050000
b10011 '
1%
#1060000
0%
#1070000
b10100 '
1%
#1080000
0%
#1090000
b10101 '
1%
#1100000
0%
#1110000
b10110 '
1%
#1120000
0%
#1130000
b10111 '
1%
#1140000
0%
#1150000
b11000 '
1%
#1160000
0%
#1170000
b11001 '
1%
#1180000
0%
#1190000
b11010 '
1%
#1200000
0%
#1210000
b11011 '
1%
#1220000
0%
#1230000
b11100 '
1%
#1240000
0%
#1250000
b11101 '
1%
#1260000
0%
#1270000
b11110 '
1%
#1280000
0%
#1290000
b1 *
1#
b11111 '
1%
#1300000
0%
#1310000
0#
0"
b10 *
b1 +
b0 '
1%
#1320000
0%
#1330000
b1 '
b10 +
1%
#1340000
0%
#1350000
b1 )
b10 '
1%
#1360000
0%
#1370000
b11 '
b10 )
1%
#1380000
0%
#1390000
1"
b11 )
b100 '
1%
#1400000
0%
#1410000
b101 '
b100 )
1%
#1420000
0%
#1430000
b101 )
b110 '
1%
#1440000
0%
#1450000
b111 '
b110 )
1%
#1460000
0%
#1470000
0"
b100 *
b111 )
b1000 '
1%
#1480000
0%
#1490000
1"
b0 *
b1001 '
b1000 )
b100 +
1%
#1500000
0%
#1510000
b0 +
b0 )
b1010 '
1%
#1520000
0%
#1530000
b1011 '
1%
#1540000
0%
#1550000
b1100 '
1%
#1560000
0%
#1570000
b1101 '
1%
#1580000
0%
#1590000
b1110 '
1%
#1600000
0%
#1610000
b1111 '
1%
#1620000
0%
#1630000
b10000 '
1%
#1640000
0%
#1650000
b10001 '
1%
#1660000
0%
#1670000
b10010 '
1%
#1680000
0%
#1690000
b10011 '
1%
#1700000
0%
#1710000
b10100 '
1%
#1720000
0%
#1730000
b10101 '
1%
#1740000
0%
#1750000
b10110 '
1%
#1760000
0%
#1770000
b10111 '
1%
#1780000
0%
#1790000
b11000 '
1%
#1800000
0%
#1810000
b11001 '
1%
#1820000
0%
#1830000
b11010 '
1%
#1840000
0%
#1850000
b11011 '
1%
#1860000
0%
#1870000
b11100 '
1%
#1880000
0%
#1890000
b11101 '
1%
#1900000
0%
#1910000
b11110 '
1%
#1920000
0%
#1930000
b1 *
1#
b11111 '
1%
#1940000
0%
#1950000
0#
0"
b10 *
b1 +
b0 '
1%
#1960000
0%
#1970000
b1 '
b10 +
1%
#1980000
0%
#1990000
b1 )
b10 '
1%
#2000000
0%
#2010000
b11 '
b10 )
1%
#2020000
0%
#2030000
1"
b11 )
b100 '
1%
#2040000
0%
#2050000
b101 '
b100 )
1%
#2060000
0%
#2070000
b101 )
b110 '
1%
#2080000
0%
#2090000
b111 '
b110 )
1%
#2100000
0%
#2110000
0"
b100 *
b111 )
b1000 '
1%
#2120000
0%
#2130000
1"
b0 *
b1001 '
b1000 )
b100 +
1%
#2140000
0%
#2150000
b0 +
b0 )
b1010 '
1%
#2160000
0%
#2170000
b1011 '
1%
#2180000
0%
#2190000
b1100 '
1%
#2200000
0%
#2210000
b1101 '
1%
#2220000
0%
#2230000
b1110 '
1%
#2240000
0%
#2250000
b1111 '
1%
#2260000
0%
#2270000
b10000 '
1%
#2280000
0%
#2290000
b10001 '
1%
#2300000
0%
#2310000
b10010 '
1%
#2320000
0%
#2330000
b10011 '
1%
#2340000
0%
#2350000
b10100 '
1%
#2360000
0%
#2370000
b10101 '
1%
#2380000
0%
#2390000
b10110 '
1%
#2400000
0%
#2410000
b10111 '
1%
#2420000
0%
#2430000
b11000 '
1%
#2440000
0%
#2450000
b11001 '
1%
#2460000
0%
#2470000
b11010 '
1%
#2480000
0%
#2490000
b11011 '
1%
#2500000
0%
#2510000
b11100 '
1%
#2520000
0%
#2530000
b11101 '
1%
#2540000
0%
#2550000
b11110 '
1%
#2560000
0%
#2570000
b1 *
1#
b11111 '
1%
#2580000
0%
#2590000
0#
0"
b10 *
b1 +
b0 '
1%
#2600000
0%
#2610000
b1 '
b10 +
1%
#2620000
0%
#2630000
b1 )
b10 '
1%
#2640000
0%
#2650000
b11 '
b10 )
1%
#2660000
0%
#2670000
1"
b11 )
b100 '
1%
#2680000
0%
#2690000
b101 '
b100 )
1%
#2700000
0%
#2710000
b101 )
b110 '
1%
#2720000
0%
#2730000
b111 '
b110 )
1%
#2740000
0%
#2750000
0"
b100 *
b111 )
b1000 '
1%
#2760000
0%
#2770000
1"
b0 *
b1001 '
b1000 )
b100 +
1%
#2780000
0%
#2790000
b0 +
b0 )
b1010 '
1%
#2800000
0%
#2810000
b1011 '
1%
#2820000
0%
#2830000
b1100 '
1%
#2840000
0%
#2850000
b1101 '
1%
#2860000
0%
#2870000
b1110 '
1%
#2880000
0%
#2890000
b1111 '
1%
#2900000
0%
#2910000
b10000 '
1%
#2920000
0%
#2930000
b10001 '
1%
#2940000
0%
#2950000
b10010 '
1%
#2960000
0%
#2970000
b10011 '
1%
#2980000
0%
#2990000
b10100 '
1%
#3000000
0%
#3010000
b10101 '
1%
#3020000
0%
#3030000
b10110 '
1%
#3040000
0%
#3050000
b10111 '
1%
#3060000
0%
#3070000
b11000 '
1%
#3080000
0%
#3090000
b11001 '
1%
#3100000
0%
#3110000
b11010 '
1%
#3120000
0%
#3130000
b11011 '
1%
#3140000
0%
#3150000
b11100 '
1%
#3160000
0%
#3170000
b11101 '
1%
#3180000
0%
#3190000
b11110 '
1%
#3200000
0%
#3210000
b1 *
1#
b11111 '
1%
#3220000
0%
#3230000
0#
0"
b10 *
b1 +
b0 '
1%
#3240000
0%
#3250000
b1 '
b10 +
1%
#3260000
0%
#3270000
b1 )
b10 '
1%
#3280000
0%
#3290000
b11 '
b10 )
1%
#3300000
0%
#3310000
1"
b11 )
b100 '
1%
#3320000
0%
#3330000
b101 '
b100 )
1%
#3340000
0%
#3350000
b101 )
b110 '
1%
#3360000
0%
#3370000
b111 '
b110 )
1%
#3380000
0%
#3390000
0"
b100 *
b111 )
b1000 '
1%
#3400000
0%
#3410000
1"
b0 *
b1001 '
b1000 )
b100 +
1%
#3420000
0%
#3430000
b0 +
b0 )
b1010 '
1%
#3440000
0%
#3450000
b1011 '
1%
#3460000
0%
#3470000
b1100 '
1%
#3480000
0%
#3490000
b1101 '
1%
#3500000
0%
#3510000
b1110 '
1%
#3520000
0%
#3530000
b1111 '
1%
#3540000
0%
#3550000
b10000 '
1%
#3560000
0%
#3570000
b10001 '
1%
#3580000
0%
#3590000
b10010 '
1%
#3600000
0%
#3610000
b10011 '
1%
#3620000
0%
#3630000
b10100 '
1%
#3640000
0%
#3650000
b10101 '
1%
#3660000
0%
#3670000
b10110 '
1%
#3680000
0%
#3690000
b10111 '
1%
#3700000
0%
#3710000
b11000 '
1%
#3720000
0%
#3730000
b11001 '
1%
#3740000
0%
#3750000
b11010 '
1%
#3760000
0%
#3770000
b11011 '
1%
#3780000
0%
#3790000
b11100 '
1%
#3800000
0%
#3810000
b11101 '
1%
#3820000
0%
#3830000
b11110 '
1%
#3840000
0%
#3850000
b1 *
1#
b11111 '
1%
#3860000
0%
#3870000
0#
0"
b10 *
b1 +
b0 '
1%
#3880000
0%
#3890000
b1 '
b10 +
1%
#3900000
0%
#3910000
b1 )
b10 '
1%
#3920000
0%
#3930000
b11 '
b10 )
1%
#3940000
0%
#3950000
1"
b11 )
b100 '
1%
#3960000
0%
#3970000
b101 '
b100 )
1%
#3980000
0%
#3990000
b101 )
b110 '
1%
#4000000
0%
#4010000
b111 '
b110 )
1%
#4020000
0%
#4030000
0"
b100 *
b111 )
b1000 '
1%
